{
  "id": 333354,
  "cast": [
    {
      "adult": false,
      "gender": 1,
      "id": 1118081,
      "known_for_department": "Acting",
      "name": "Bethany Joy Lenz",
      "original_name": "Bethany Joy Lenz",
      "popularity": 2.4328,
      "profile_path": "/wdzam5aHZyWwPSbxQz8iL9wIpR7.jpg",
      "cast_id": 6,
      "character": "Julie Riley",
      "credit_id": "57a26a469251413e9a000aae",
      "order": 0
    },
    {
      "adult": false,
      "gender": 2,
      "id": 2047,
      "known_for_department": "Acting",
      "name": "Danny Glover",
      "original_name": "Danny Glover",
      "popularity": 3.8596,
      "profile_path": "/2PJbpI9AyuhG4SWUIDxZwuBnuMb.jpg",
      "cast_id": 7,
      "character": "Constable Haagen",
      "credit_id": "57a26a5f92514140a5000ada",
      "order": 1
    },
    {
      "adult": false,
      "gender": 2,
      "id": 27031,
      "known_for_department": "Acting",
      "name": "Tim Griffin",
      "original_name": "Tim Griffin",
      "popularity": 2.0915,
      "profile_path": "/i3BRPyeBg7CQnGLsHxA6gpnDzDj.jpg",
      "cast_id": 27,
      "character": "Actor",
      "credit_id": "57eae02192514132b20002b7",
      "order": 2
    },
    {
      "adult": false,
      "gender": 2,
      "id": 7498,
      "known_for_department": "Acting",
      "name": "Eion Bailey",
      "original_name": "Eion Bailey",
      "popularity": 2.3779,
      "profile_path": "/3DW13W47cKk4LQZwS4EvRaNBoVu.jpg",
      "cast_id": 8,
      "character": "Kevin Riley",
      "credit_id": "57a26a78925141577e0003a5",
      "order": 3
    },
    {
      "adult": false,
      "gender": 2,
      "id": 1261694,
      "known_for_department": "Acting",
      "name": "Barkhad Abdi",
      "original_name": "Barkhad Abdi",
      "popularity": 2.0855,
      "profile_path": "/utfeg8GnGyW3aVNcRfhII9RCXB6.jpg",
      "cast_id": 3,
      "character": "Miguel Kaba",
      "credit_id": "551868a8c3a36862ef0048b7",
      "order": 4
    },
    {
      "adult": false,
      "gender": 2,
      "id": 24435,
      "known_for_department": "Acting",
      "name": "Jack Wallace",
      "original_name": "Jack Wallace",
      "popularity": 0.9347,
      "profile_path": "/mg23nIdVa4MzUOHuEAdUB0kyZUV.jpg",
      "cast_id": 9,
      "character": "Lucas",
      "credit_id": "57a26a969251413e9a000ace",
      "order": 5
    },
    {
      "adult": false,
      "gender": 0,
      "id": 1661025,
      "known_for_department": "Acting",
      "name": "Jorge Navarro",
      "original_name": "Jorge Navarro",
      "popularity": 0.2781,
      "profile_path": "/A26H74Qv1Gk7eQcQ0sDfpIewmp3.jpg",
      "cast_id": 10,
      "character": "Rental Attendant",
      "credit_id": "57a26ac392514140a5000aff",
      "order": 6
    },
    {
      "adult": false,
      "gender": 2,
      "id": 1652853,
      "known_for_department": "Acting",
      "name": "Mauricio Alemañy",
      "original_name": "Mauricio Alemañy",
      "popularity": 1.2171,
      "profile_path": "/jRjBgafBlfOaoVSYc6AuoKL4YVO.jpg",
      "cast_id": 11,
      "character": "Andy Riley",
      "credit_id": "57a26af8c3a3682fa7000c0e",
      "order": 7
    },
    {
      "adult": false,
      "gender": 2,
      "id": 1608740,
      "known_for_department": "Acting",
      "name": "Xavier Morales",
      "original_name": "Xavier Morales",
      "popularity": 0.4537,
      "profile_path": "/cXb0xksR2SmuJEoUCOIr7NyBZRt.jpg",
      "cast_id": 12,
      "character": "Police",
      "credit_id": "57a26b0b9251414055000b61",
      "order": 8
    },
    {
      "adult": false,
      "gender": 1,
      "id": 1685662,
      "known_for_department": "Acting",
      "name": "Amber Rivera",
      "original_name": "Amber Rivera",
      "popularity": 1.8213,
      "profile_path": "/bHA6eTOHpyFaiybgRUfFRKIJeXG.jpg",
      "cast_id": 26,
      "character": "U.S. Embassy Clerk",
      "credit_id": "57eae00292514132c10002b8",
      "order": 9
    },
    {
      "adult": false,
      "gender": 0,
      "id": 1459066,
      "known_for_department": "Acting",
      "name": "Marilinda Rivera",
      "original_name": "Marilinda Rivera",
      "popularity": 0.155,
      "profile_path": "/yi0GdbtzJj0PlZznrpcDSScgITg.jpg",
      "cast_id": 28,
      "character": "Doctor Bethel",
      "credit_id": "57eae02d92514132c40002b4",
      "order": 10
    },
    {
      "adult": false,
      "gender": 0,
      "id": 1645002,
      "known_for_department": "Acting",
      "name": "Edward Lee Thompson",
      "original_name": "Edward Lee Thompson",
      "popularity": 0.6182,
      "profile_path": null,
      "cast_id": 29,
      "character": "Hotel guest",
      "credit_id": "57eae06f92514132b20002ce",
      "order": 11
    },
    {
      "adult": false,
      "gender": 0,
      "id": 1685663,
      "known_for_department": "Acting",
      "name": "James O. Beatty",
      "original_name": "James O. Beatty",
      "popularity": 0.2798,
      "profile_path": "/gWgzP5b0XLBB1OTnEh3509JYZa2.jpg",
      "cast_id": 30,
      "character": "Tourist",
      "credit_id": "57eae08992514132ba0002d8",
      "order": 12
    },
    {
      "adult": false,
      "gender": 0,
      "id": 1685664,
      "known_for_department": "Acting",
      "name": "James Gordon Jennings",
      "original_name": "James Gordon Jennings",
      "popularity": 0.1788,
      "profile_path": "/cynrSiZ46PSLPVwxSrIckJZTpP2.jpg",
      "cast_id": 31,
      "character": "Captain Gerald, USCG",
      "credit_id": "57eae0bc92514132b80002ca",
      "order": 13
    },
    {
      "adult": false,
      "gender": 0,
      "id": 1685301,
      "known_for_department": "Sound",
      "name": "Welmo Romero",
      "original_name": "Welmo Romero",
      "popularity": 0.0593,
      "profile_path": null,
      "cast_id": 35,
      "character": "Roger",
      "credit_id": "5957dede9251410cbc00dfb7",
      "order": 14
    },
    {
      "adult": false,
      "gender": 0,
      "id": 1621276,
      "known_for_department": "Acting",
      "name": "Bryan López Vázquez",
      "original_name": "Bryan López Vázquez",
      "popularity": 0.5489,
      "profile_path": null,
      "cast_id": 32,
      "character": "Bus People (uncredited)",
      "credit_id": "57eae0edc3a36843610002c2",
      "order": 15
    },
    {
      "adult": false,
      "gender": 0,
      "id": 1685665,
      "known_for_department": "Acting",
      "name": "Franchesca Soto",
      "original_name": "Franchesca Soto",
      "popularity": 0.1204,
      "profile_path": null,
      "cast_id": 33,
      "character": "Extra (uncredited)",
      "credit_id": "57eae12392514132c40002fb",
      "order": 16
    }
  ],
  "crew": [
    {
      "adult": false,
      "gender": 2,
      "id": 1115305,
      "known_for_department": "Directing",
      "name": "Phil Volken",
      "original_name": "Phil Volken",
      "popularity": 0.3058,
      "profile_path": null,
      "credit_id": "5518688bc3a3685cfa002c0b",
      "department": "Directing",
      "job": "Director"
    },
    {
      "adult": false,
      "gender": 2,
      "id": 1115305,
      "known_for_department": "Directing",
      "name": "Phil Volken",
      "original_name": "Phil Volken",
      "popularity": 0.3058,
      "profile_path": null,
      "credit_id": "55186894c3a36862ef0048b3",
      "department": "Writing",
      "job": "Writer"
    },
    {
      "adult": false,
      "gender": 0,
      "id": 1661026,
      "known_for_department": "Production",
      "name": "Alina Shraybman",
      "original_name": "Alina Shraybman",
      "popularity": 0.0607,
      "profile_path": null,
      "credit_id": "57a26b6e92514148440008d6",
      "department": "Production",
      "job": "Producer"
    },
    {
      "adult": false,
      "gender": 2,
      "id": 1115305,
      "known_for_department": "Directing",
      "name": "Phil Volken",
      "original_name": "Phil Volken",
      "popularity": 0.3058,
      "profile_path": null,
      "credit_id": "57a26b7bc3a3682d9e000e85",
      "department": "Production",
      "job": "Producer"
    },
    {
      "adult": false,
      "gender": 1,
      "id": 1618636,
      "known_for_department": "Production",
      "name": "Leah Aldarondo",
      "original_name": "Leah Aldarondo",
      "popularity": 0.1131,
      "profile_path": null,
      "credit_id": "57a26b899251413fd0000bbd",
      "department": "Production",
      "job": "Line Producer"
    },
    {
      "adult": false,
      "gender": 1,
      "id": 1613773,
      "known_for_department": "Costume & Make-Up",
      "name": "Suzanne Krim",
      "original_name": "Suzanne Krim",
      "popularity": 0.3448,
      "profile_path": null,
      "credit_id": "57a26bac9251414055000b8c",
      "department": "Costume & Make-Up",
      "job": "Costume Design"
    },
    {
      "adult": false,
      "gender": 0,
      "id": 1638706,
      "known_for_department": "Art",
      "name": "Jimmy Santos",
      "original_name": "Jimmy Santos",
      "popularity": 0.1459,
      "profile_path": null,
      "credit_id": "57a26bc7925141403e000bc4",
      "department": "Costume & Make-Up",
      "job": "Set Dressing Artist"
    },
    {
      "adult": false,
      "gender": 1,
      "id": 1616485,
      "known_for_department": "Production",
      "name": "Annabelle Mullen",
      "original_name": "Annabelle Mullen",
      "popularity": 0.2734,
      "profile_path": null,
      "credit_id": "57a26bfec3a3682d9e000eb2",
      "department": "Production",
      "job": "Production Supervisor"
    },
    {
      "adult": false,
      "gender": 0,
      "id": 1561043,
      "known_for_department": "Art",
      "name": "Gerardo José Vega",
      "original_name": "Gerardo José Vega",
      "popularity": 0.5745,
      "profile_path": null,
      "credit_id": "57a26c12925141577e000436",
      "department": "Art",
      "job": "Production Design"
    },
    {
      "adult": false,
      "gender": 2,
      "id": 1613774,
      "known_for_department": "Art",
      "name": "Fernando Carrión",
      "original_name": "Fernando Carrión",
      "popularity": 0.2001,
      "profile_path": null,
      "credit_id": "57a26c2ac3a3682fa7000c79",
      "department": "Art",
      "job": "Production Design"
    },
    {
      "adult": false,
      "gender": 0,
      "id": 1613913,
      "known_for_department": "Directing",
      "name": "Kemel Jamís",
      "original_name": "Kemel Jamís",
      "popularity": 1.0672,
      "profile_path": null,
      "credit_id": "57a26c3ec3a3682fa7000c80",
      "department": "Directing",
      "job": "Assistant Director"
    },
    {
      "adult": false,
      "gender": 0,
      "id": 1661028,
      "known_for_department": "Directing",
      "name": "Vanessa Rodríguez Murphy",
      "original_name": "Vanessa Rodríguez Murphy",
      "popularity": 0.2461,
      "profile_path": null,
      "credit_id": "57a26c73925141411a000b09",
      "department": "Directing",
      "job": "Assistant Director"
    },
    {
      "adult": false,
      "gender": 2,
      "id": 1594173,
      "known_for_department": "Acting",
      "name": "Ramiro 'Ramir' Delgado Ruiz",
      "original_name": "Ramiro 'Ramir' Delgado Ruiz",
      "popularity": 0.8424,
      "profile_path": "/y7qqQOOnEhSWz5aUkt7c3hQ52R0.jpg",
      "credit_id": "57a26c98c3a3682b72000f4a",
      "department": "Production",
      "job": "Casting"
    },
    {
      "adult": false,
      "gender": 2,
      "id": 1403565,
      "known_for_department": "Camera",
      "name": "Carlos Zayas",
      "original_name": "Carlos Zayas",
      "popularity": 0.4929,
      "profile_path": null,
      "credit_id": "57a26cab9251414055000beb",
      "department": "Camera",
      "job": "Camera Operator"
    },
    {
      "adult": false,
      "gender": 0,
      "id": 1661030,
      "known_for_department": "Art",
      "name": "Pamela Nicole Padilla",
      "original_name": "Pamela Nicole Padilla",
      "popularity": 0.1966,
      "profile_path": null,
      "credit_id": "57a26cdf925141403e000c42",
      "department": "Crew",
      "job": "Property Master"
    },
    {
      "adult": false,
      "gender": 0,
      "id": 72110,
      "known_for_department": "Production",
      "name": "Ines Mongil-Echandi",
      "original_name": "Ines Mongil-Echandi",
      "popularity": 0.4592,
      "profile_path": null,
      "credit_id": "57eae154c3a36843640002b1",
      "department": "Production",
      "job": "Unit Production Manager"
    },
    {
      "adult": false,
      "gender": 0,
      "id": 2234753,
      "known_for_department": "Camera",
      "name": "Helge Gerull",
      "original_name": "Helge Gerull",
      "popularity": 0.1265,
      "profile_path": null,
      "credit_id": "5c58ac1792514116fc5b051e",
      "department": "Camera",
      "job": "Director of Photography"
    },
    {
      "adult": false,
      "gender": 2,
      "id": 1115305,
      "known_for_department": "Directing",
      "name": "Phil Volken",
      "original_name": "Phil Volken",
      "popularity": 0.3058,
      "profile_path": null,
      "credit_id": "5c58ac33c3a36805e8873c61",
      "department": "Editing",
      "job": "Editor"
    },
    {
      "adult": false,
      "gender": 2,
      "id": 37012,
      "known_for_department": "Editing",
      "name": "Brad Wilhite",
      "original_name": "Brad Wilhite",
      "popularity": 0.8265,
      "profile_path": null,
      "credit_id": "5c58ac4e0e0a265e19d7e372",
      "department": "Editing",
      "job": "Editor"
    },
    {
      "adult": false,
      "gender": 2,
      "id": 1043784,
      "known_for_department": "Directing",
      "name": "Gerardo Vera",
      "original_name": "Gerardo Vera",
      "popularity": 1.7044,
      "profile_path": "/cHmSsmTAf7AaIKSs8nHaZ99zWnN.jpg",
      "credit_id": "5c58acb7c3a36872908b942b",
      "department": "Art",
      "job": "Art Direction"
    },
    {
      "adult": false,
      "gender": 0,
      "id": 2234754,
      "known_for_department": "Art",
      "name": "Gregorio Barreto",
      "original_name": "Gregorio Barreto",
      "popularity": 0.1355,
      "profile_path": null,
      "credit_id": "5c58acde92514151a96701b3",
      "department": "Art",
      "job": "Set Decoration"
    },
    {
      "adult": false,
      "gender": 0,
      "id": 1100139,
      "known_for_department": "Costume & Make-Up",
      "name": "Angie Olmedo",
      "original_name": "Angie Olmedo",
      "popularity": 0.0777,
      "profile_path": null,
      "credit_id": "5c58ad060e0a26185ac9720b",
      "department": "Costume & Make-Up",
      "job": "Costume Design"
    },
    {
      "adult": false,
      "gender": 0,
      "id": 1315842,
      "known_for_department": "Costume & Make-Up",
      "name": "Laura Calvo",
      "original_name": "Laura Calvo",
      "popularity": 0.2814,
      "profile_path": null,
      "credit_id": "5c58ad350e0a26494de4c6bd",
      "department": "Costume & Make-Up",
      "job": "Key Makeup Artist"
    },
    {
      "adult": false,
      "gender": 0,
      "id": 1917993,
      "known_for_department": "Costume & Make-Up",
      "name": "Angela Gurule",
      "original_name": "Angela Gurule",
      "popularity": 0.1394,
      "profile_path": null,
      "credit_id": "5c58ad7b9251410e1d52b47e",
      "department": "Costume & Make-Up",
      "job": "Key Hair Stylist"
    },
    {
      "adult": false,
      "gender": 0,
      "id": 2196541,
      "known_for_department": "Costume & Make-Up",
      "name": "Marielena Ramirez",
      "original_name": "Marielena Ramirez",
      "popularity": 0.307,
      "profile_path": null,
      "credit_id": "5c58ade00e0a265e19d7e84a",
      "department": "Costume & Make-Up",
      "job": "Key Makeup Artist"
    },
    {
      "adult": false,
      "gender": 0,
      "id": 2234756,
      "known_for_department": "Costume & Make-Up",
      "name": "Rodyloida Ruiz",
      "original_name": "Rodyloida Ruiz",
      "popularity": 0.213,
      "profile_path": null,
      "credit_id": "5c58ae010e0a265e19d7e940",
      "department": "Costume & Make-Up",
      "job": "Hairstylist"
    },
    {
      "adult": false,
      "gender": 2,
      "id": 2191962,
      "known_for_department": "Production",
      "name": "Zebulun Huling",
      "original_name": "Zebulun Huling",
      "popularity": 0.1728,
      "profile_path": null,
      "credit_id": "5c58ae310e0a263ccde686c1",
      "department": "Directing",
      "job": "First Assistant Director"
    },
    {
      "adult": false,
      "gender": 0,
      "id": 2234758,
      "known_for_department": "Art",
      "name": "Richard Alfaro",
      "original_name": "Richard Alfaro",
      "popularity": 0.0833,
      "profile_path": null,
      "credit_id": "5c58ae68c3a36826a6878056",
      "department": "Art",
      "job": "Construction Coordinator"
    },
    {
      "adult": false,
      "gender": 0,
      "id": 1922708,
      "known_for_department": "Sound",
      "name": "Gad Emile Zeitune",
      "original_name": "Gad Emile Zeitune",
      "popularity": 0.3609,
      "profile_path": null,
      "credit_id": "5c58aee6c3a3687199873e55",
      "department": "Sound",
      "job": "Original Music Composer"
    },
    {
      "adult": false,
      "gender": 0,
      "id": 1618258,
      "known_for_department": "Sound",
      "name": "Daniele Carli",
      "original_name": "Daniele Carli",
      "popularity": 0.3786,
      "profile_path": null,
      "credit_id": "5c58af27925141544866bc2e",
      "department": "Sound",
      "job": "Sound Designer"
    },
    {
      "adult": false,
      "gender": 0,
      "id": 2234759,
      "known_for_department": "Sound",
      "name": "Sandra Gallo-Harris",
      "original_name": "Sandra Gallo-Harris",
      "popularity": 0.1537,
      "profile_path": null,
      "credit_id": "5c58af3dc3a368478ca425a7",
      "department": "Sound",
      "job": "Boom Operator"
    },
    {
      "adult": false,
      "gender": 0,
      "id": 2234761,
      "known_for_department": "Sound",
      "name": "Maira García",
      "original_name": "Maira García",
      "popularity": 0.0535,
      "profile_path": null,
      "credit_id": "5c58af4a92514151a96707c6",
      "department": "Sound",
      "job": "Boom Operator"
    },
    {
      "adult": false,
      "gender": 2,
      "id": 115810,
      "known_for_department": "Sound",
      "name": "Yagmur Kaplan",
      "original_name": "Yagmur Kaplan",
      "popularity": 0.3688,
      "profile_path": "/91qHgHQTUoqN41Mq2IwMTel3Oro.jpg",
      "credit_id": "5c58af640e0a263ccde68a1a",
      "department": "Sound",
      "job": "Sound Re-Recording Mixer"
    },
    {
      "adult": false,
      "gender": 0,
      "id": 1734414,
      "known_for_department": "Sound",
      "name": "Josh Kupanoff",
      "original_name": "Josh Kupanoff",
      "popularity": 0.0594,
      "profile_path": null,
      "credit_id": "5c58af7892514116fc5b0dc2",
      "department": "Sound",
      "job": "Foley Editor"
    },
    {
      "adult": false,
      "gender": 0,
      "id": 2140850,
      "known_for_department": "Sound",
      "name": "Jifu Li",
      "original_name": "Jifu Li",
      "popularity": 0.3948,
      "profile_path": null,
      "credit_id": "5c58aff89251415e346aaf35",
      "department": "Sound",
      "job": "Sound Effects Editor"
    },
    {
      "adult": false,
      "gender": 0,
      "id": 1618257,
      "known_for_department": "Sound",
      "name": "Cody Morris",
      "original_name": "Cody Morris",
      "popularity": 0.7187,
      "profile_path": null,
      "credit_id": "5c58b0109251410e1d52bbbb",
      "department": "Sound",
      "job": "Foley Editor"
    },
    {
      "adult": false,
      "gender": 2,
      "id": 1617014,
      "known_for_department": "Crew",
      "name": "Luis Raúl Alcocer",
      "original_name": "Luis Raúl Alcocer",
      "popularity": 0.2515,
      "profile_path": null,
      "credit_id": "5c58b083c3a36871998743fb",
      "department": "Crew",
      "job": "Stunt Coordinator"
    },
    {
      "adult": false,
      "gender": 0,
      "id": 1830690,
      "known_for_department": "Acting",
      "name": "Angel R. Pagan Colon",
      "original_name": "Angel R. Pagan Colon",
      "popularity": 0.1358,
      "profile_path": null,
      "credit_id": "5c58b0979251415e346ab04b",
      "department": "Crew",
      "job": "Stunt Coordinator"
    },
    {
      "adult": false,
      "gender": 0,
      "id": 1683046,
      "known_for_department": "Camera",
      "name": "José L. Alvarado",
      "original_name": "José L. Alvarado",
      "popularity": 0.0988,
      "profile_path": null,
      "credit_id": "5c58b0ad0e0a26494de4d120",
      "department": "Camera",
      "job": "Dolly Grip"
    },
    {
      "adult": false,
      "gender": 0,
      "id": 2234766,
      "known_for_department": "Camera",
      "name": "Willy MontaÑez",
      "original_name": "Willy MontaÑez",
      "popularity": 0.1714,
      "profile_path": null,
      "credit_id": "5c58b0ff0e0a265e19d7eed4",
      "department": "Camera",
      "job": "First Assistant Camera"
    },
    {
      "adult": false,
      "gender": 0,
      "id": 2234767,
      "known_for_department": "Lighting",
      "name": "Vincent O'Carroll",
      "original_name": "Vincent O'Carroll",
      "popularity": 0.352,
      "profile_path": null,
      "credit_id": "5c58b10ec3a36826a6878bd8",
      "department": "Lighting",
      "job": "Gaffer"
    },
    {
      "adult": false,
      "gender": 0,
      "id": 2234768,
      "known_for_department": "Camera",
      "name": "Robert Lucas Pena",
      "original_name": "Robert Lucas Pena",
      "popularity": 0.1317,
      "profile_path": null,
      "credit_id": "5c58b124c3a36871998744e2",
      "department": "Camera",
      "job": "Key Grip"
    },
    {
      "adult": false,
      "gender": 0,
      "id": 2234769,
      "known_for_department": "Lighting",
      "name": "Marcos Pesquera",
      "original_name": "Marcos Pesquera",
      "popularity": 0.0936,
      "profile_path": null,
      "credit_id": "5c58b131c3a3687199874517",
      "department": "Lighting",
      "job": "Gaffer"
    },
    {
      "adult": false,
      "gender": 2,
      "id": 2234770,
      "known_for_department": "Camera",
      "name": "Marc Polanski",
      "original_name": "Marc Polanski",
      "popularity": 0.5199,
      "profile_path": null,
      "credit_id": "5c58b1410e0a260506cbb896",
      "department": "Camera",
      "job": "Key Grip"
    },
    {
      "adult": false,
      "gender": 0,
      "id": 1403567,
      "known_for_department": "Camera",
      "name": "Kenneth Rexach",
      "original_name": "Kenneth Rexach",
      "popularity": 0.1984,
      "profile_path": null,
      "credit_id": "5c58b15cc3a3684246879303",
      "department": "Camera",
      "job": "Still Photographer"
    },
    {
      "adult": false,
      "gender": 0,
      "id": 2234771,
      "known_for_department": "Camera",
      "name": "Carlos Rafi Rivera",
      "original_name": "Carlos Rafi Rivera",
      "popularity": 0.2922,
      "profile_path": null,
      "credit_id": "5c58b17492514135b052805f",
      "department": "Camera",
      "job": "First Assistant Camera"
    },
    {
      "adult": false,
      "gender": 0,
      "id": 2234772,
      "known_for_department": "Lighting",
      "name": "Mark Seger",
      "original_name": "Mark Seger",
      "popularity": 0.2487,
      "profile_path": null,
      "credit_id": "5c58b18ec3a368478ca42ade",
      "department": "Lighting",
      "job": "Best Boy Electric"
    },
    {
      "adult": false,
      "gender": 0,
      "id": 2234773,
      "known_for_department": "Camera",
      "name": "Erik Stapelfeldt",
      "original_name": "Erik Stapelfeldt",
      "popularity": 0.4933,
      "profile_path": null,
      "credit_id": "5c58b1a792514116fc5b14ae",
      "department": "Camera",
      "job": "First Assistant \"A\" Camera"
    },
    {
      "adult": false,
      "gender": 0,
      "id": 1579382,
      "known_for_department": "Sound",
      "name": "Oren Yaacoby",
      "original_name": "Oren Yaacoby",
      "popularity": 0.1646,
      "profile_path": null,
      "credit_id": "5c58b1d9c3a36805e8874cd4",
      "department": "Sound",
      "job": "Music Editor"
    },
    {
      "adult": false,
      "gender": 1,
      "id": 2089518,
      "known_for_department": "Crew",
      "name": "Lorri Bearbower",
      "original_name": "Lorri Bearbower",
      "popularity": 0.0952,
      "profile_path": null,
      "credit_id": "5c58b1ff92514157df5309c5",
      "department": "Crew",
      "job": "Studio Teacher"
    },
    {
      "adult": false,
      "gender": 1,
      "id": 1836960,
      "known_for_department": "Production",
      "name": "Charissa McLain",
      "original_name": "Charissa McLain",
      "popularity": 0.3752,
      "profile_path": null,
      "credit_id": "5c58b2380e0a26567acc3a49",
      "department": "Production",
      "job": "Production Coordinator"
    },
    {
      "adult": false,
      "gender": 0,
      "id": 1395035,
      "known_for_department": "Directing",
      "name": "Liliana M. Molina",
      "original_name": "Liliana M. Molina",
      "popularity": 0.1936,
      "profile_path": null,
      "credit_id": "5c58b283c3a3687199874783",
      "department": "Directing",
      "job": "Script Coordinator"
    },
    {
      "adult": false,
      "gender": 0,
      "id": 2234774,
      "known_for_department": "Crew",
      "name": "Rosa Pacheco",
      "original_name": "Rosa Pacheco",
      "popularity": 0.0981,
      "profile_path": null,
      "credit_id": "5c58b2a89251410e1d52c113",
      "department": "Crew",
      "job": "Studio Teacher"
    },
    {
      "adult": false,
      "gender": 0,
      "id": 2234775,
      "known_for_department": "Production",
      "name": "Nilda Perez",
      "original_name": "Nilda Perez",
      "popularity": 0.0533,
      "profile_path": null,
      "credit_id": "5c58b2c592514157df530c2f",
      "department": "Production",
      "job": "Production Coordinator"
    },
    {
      "adult": false,
      "gender": 1,
      "id": 1611753,
      "known_for_department": "Costume & Make-Up",
      "name": "Ybelka Hurtado",
      "original_name": "Ybelka Hurtado",
      "popularity": 0.3014,
      "profile_path": null,
      "credit_id": "6792755583d182404eead569",
      "department": "Costume & Make-Up",
      "job": "Makeup & Hair Assistant"
    }
  ]
}