{
  "adult": false,
  "backdrop_path": "/wEEQJM6IE4nIWBKdLddBWKGoBxv.jpg",
  "belongs_to_collection": null,
  "budget": 0,
  "genres": [
    {
      "id": 35,
      "name": "Comedy"
    }
  ],
  "homepage": "",
  "id": 509421,
  "imdb_id": "tt6131126",
  "origin_country": [
    "MX"
  ],
  "original_language": "es",
  "original_title": "Todo Mal",
  "overview": "When a young diplomat manages to get the Austrian government to return the Plume of Moctezuma to Mexico for an exhibition, his life quickly falls apart.",
  "popularity": 2.6095,
  "poster_path": "/v7038rxSU26SOacXEpAyvoFS8aJ.jpg",
  "production_companies": [
    {
      "id": 133016,
      "logo_path": null,
      "name": "Traziende Films",
      "origin_country": "MX"
    },
    {
      "id": 96980,
      "logo_path": null,
      "name": "Peligrosa",
      "origin_country": "MX"
    },
    {
      "id": 74139,
      "logo_path": null,
      "name": "EFICINE 189",
      "origin_country": "MX"
    },
    {
      "id": 7570,
      "logo_path": "/gW8dfVtl1JsGIiLnvglea1OHHVr.png",
      "name": "Videocine",
      "origin_country": "MX"
    }
  ],
  "production_countries": [
    {
      "iso_3166_1": "MX",
      "name": "Mexico"
    }
  ],
  "release_date": "2018-03-16",
  "revenue": 0,
  "runtime": 102,
  "spoken_languages": [
    {
      "english_name": "Spanish",
      "iso_639_1": "es",
      "name": "Español"
    }
  ],
  "status": "Released",
  "tagline": "",
  "title": "Everything's Gone Wrong!",
  "video": false,
  "vote_average": 7.1,
  "vote_count": 50
}