{
  "adult": false,
  "backdrop_path": "/5k7TRCxU84BiOpibPAJByoG3cbe.jpg",
  "belongs_to_collection": null,
  "budget": 1000000,
  "genres": [
    {
      "id": 10402,
      "name": "Music"
    },
    {
      "id": 18,
      "name": "Drama"
    }
  ],
  "homepage": "",
  "id": 15697,
  "imdb_id": "tt0050556",
  "origin_country": [
    "US"
  ],
  "original_language": "en",
  "original_title": "Jailhouse Rock",
  "overview": "After serving time for manslaughter, young Vince Everett becomes a teenage rock star.",
  "popularity": 2.675,
  "poster_path": "/iSlddodPAnPuRPr7Cc8AYvaNHSR.jpg",
  "production_companies": [
    {
      "id": 100,
      "logo_path": null,
      "name": "Avon Productions",
      "origin_country": "US"
    },
    {
      "id": 21,
      "logo_path": "/usUnaYV6hQnlVAXP6r4HwrlLFPG.png",
      "name": "Metro-Goldwyn-Mayer",
      "origin_country": "US"
    }
  ],
  "production_countries": [
    {
      "iso_3166_1": "US",
      "name": "United States of America"
    }
  ],
  "release_date": "1957-01-17",
  "revenue": 4000000,
  "runtime": 96,
  "spoken_languages": [
    {
      "english_name": "English",
      "iso_639_1": "en",
      "name": "English"
    }
  ],
  "status": "Released",
  "tagline": "Elvis in Action as Never Before!",
  "title": "Jailhouse Rock",
  "video": false,
  "vote_average": 6.158,
  "vote_count": 183
}