{
  "id": 290595,
  "cast": [
    {
      "adult": false,
      "gender": 2,
      "id": 74568,
      "known_for_department": "Acting",
      "name": "Chris Hemsworth",
      "original_name": "Chris Hemsworth",
      "popularity": 5.6687,
      "profile_path": "/piQGdoIQOF3C1EI5cbYZLAW1gfj.jpg",
      "cast_id": 0,
      "character": "The Huntsman",
      "credit_id": "5409a39ec3a36812c30019a0",
      "order": 0
    },
    {
      "adult": false,
      "gender": 1,
      "id": 6885,
      "known_for_department": "Acting",
      "name": "Charlize Theron",
      "original_name": "Charlize Theron",
      "popularity": 7.0858,
      "profile_path": "/ie1KbeYFG5E0GVr1QP7tDNuXvga.jpg",
      "cast_id": 1,
      "character": "Queen Ravenna",
      "credit_id": "5409a3acc3a36812bf0019bd",
      "order": 1
    },
    {
      "adult": false,
      "gender": 1,
      "id": 5081,
      "known_for_department": "Acting",
      "name": "Emily Blunt",
      "original_name": "Emily Blunt",
      "popularity": 17.1643,
      "profile_path": "/5nCSG5TL1bP1geD8aaBfaLnLLCD.jpg",
      "cast_id": 3,
      "character": "Freya",
      "credit_id": "54d9eb979251410659000f10",
      "order": 2
    },
    {
      "adult": false,
      "gender": 1,
      "id": 83002,
      "known_for_department": "Acting",
      "name": "Jessica Chastain",
      "original_name": "Jessica Chastain",
      "popularity": 6.8051,
      "profile_path": "/bXFXSlfCzoE5Py7KBP9P0Y0Ot1v.jpg",
      "cast_id": 4,
      "character": "Sara",
      "credit_id": "54ee14f9c3a3686b9a001df7",
      "order": 3
    },
    {
      "adult": false,
      "gender": 2,
      "id": 11109,
      "known_for_department": "Acting",
      "name": "Nick Frost",
      "original_name": "Nick Frost",
      "popularity": 3.9371,
      "profile_path": "/2CHS4t6miNGLgMQAjhFqb4fFuKS.jpg",
      "cast_id": 10,
      "character": "Nion",
      "credit_id": "552f5e1a9251415be8001343",
      "order": 4
    },
    {
      "adult": false,
      "gender": 2,
      "id": 237455,
      "known_for_department": "Acting",
      "name": "Sam Claflin",
      "original_name": "Sam Claflin",
      "popularity": 7.5772,
      "profile_path": "/e5CU4tjCNZFfm7ITmZfzjZse2Bb.jpg",
      "cast_id": 16,
      "character": "William",
      "credit_id": "564a6de6c3a3686037000e28",
      "order": 5
    },
    {
      "adult": false,
      "gender": 2,
      "id": 47632,
      "known_for_department": "Acting",
      "name": "Rob Brydon",
      "original_name": "Rob Brydon",
      "popularity": 1.7496,
      "profile_path": "/xoKLZVwzaUgTUEvPX4vymXpC1fU.jpg",
      "cast_id": 12,
      "character": "Gryff",
      "credit_id": "552f5e31c3a3685951001b56",
      "order": 6
    },
    {
      "adult": false,
      "gender": 1,
      "id": 110080,
      "known_for_department": "Acting",
      "name": "Sheridan Smith",
      "original_name": "Sheridan Smith",
      "popularity": 1.7452,
      "profile_path": "/6vHbF7cO4vWr8Tm8wxfZDHpO32e.jpg",
      "cast_id": 11,
      "character": "Mrs. Bromwyn",
      "credit_id": "552f5e289251413838004a6f",
      "order": 7
    },
    {
      "adult": false,
      "gender": 1,
      "id": 237020,
      "known_for_department": "Acting",
      "name": "Alexandra Roach",
      "original_name": "Alexandra Roach",
      "popularity": 2.2462,
      "profile_path": "/qyaUWoAi6RFYEQcnFgrEZ4aWxS7.jpg",
      "cast_id": 13,
      "character": "Doreena",
      "credit_id": "552f5e3a9251415be8001348",
      "order": 8
    },
    {
      "adult": false,
      "gender": 2,
      "id": 1479869,
      "known_for_department": "Acting",
      "name": "Ṣọpẹ́ Dìrísù",
      "original_name": "Ṣọpẹ́ Dìrísù",
      "popularity": 2.3139,
      "profile_path": "/k9Ayv1XflEbEI599rqgf6Y4gcFY.jpg",
      "cast_id": 25,
      "character": "Tull",
      "credit_id": "57af317bc3a36802dc0028ca",
      "order": 9
    },
    {
      "adult": false,
      "gender": 1,
      "id": 1282054,
      "known_for_department": "Acting",
      "name": "Sophie Cookson",
      "original_name": "Sophie Cookson",
      "popularity": 2.2221,
      "profile_path": "/3HrHnpDFjHIdHNeEyhEdzh6L6jd.jpg",
      "cast_id": 18,
      "character": "Pippa",
      "credit_id": "564a6e1c9251414dd1000d56",
      "order": 10
    },
    {
      "adult": false,
      "gender": 2,
      "id": 563559,
      "known_for_department": "Acting",
      "name": "Sam Hazeldine",
      "original_name": "Sam Hazeldine",
      "popularity": 1.9651,
      "profile_path": "/lzxuRO9hkI2LWGUCXssemiIUgeX.jpg",
      "cast_id": 19,
      "character": "Leifr",
      "credit_id": "564c9e96c3a36860370074d8",
      "order": 11
    },
    {
      "adult": false,
      "gender": 2,
      "id": 228866,
      "known_for_department": "Acting",
      "name": "Colin Morgan",
      "original_name": "Colin Morgan",
      "popularity": 2.3198,
      "profile_path": "/jeSLhhfUIZR3UQGGhtYTk0J2I5.jpg",
      "cast_id": 17,
      "character": "Duke of Blackwood",
      "credit_id": "564a6e0a9251414dcb000df7",
      "order": 12
    },
    {
      "adult": false,
      "gender": 2,
      "id": 1665602,
      "known_for_department": "Acting",
      "name": "Conrad Khan",
      "original_name": "Conrad Khan",
      "popularity": 1.7885,
      "profile_path": "/4luIAGWxjNlvQIslUI8Z1dDbyGB.jpg",
      "cast_id": 26,
      "character": "Young Eric",
      "credit_id": "57af322692514172c9002c0b",
      "order": 13
    },
    {
      "adult": false,
      "gender": 1,
      "id": 1665603,
      "known_for_department": "Acting",
      "name": "Niamh Walter",
      "original_name": "Niamh Walter",
      "popularity": 0.3397,
      "profile_path": "/2uVT5922hpYxnJ3OQ3n1M111MEl.jpg",
      "cast_id": 27,
      "character": "Young Sara",
      "credit_id": "57af32bdc3a36821c6004f7f",
      "order": 14
    },
    {
      "adult": false,
      "gender": 2,
      "id": 1665604,
      "known_for_department": "Acting",
      "name": "Nana Agyeman-Bediako",
      "original_name": "Nana Agyeman-Bediako",
      "popularity": 0.6968,
      "profile_path": "/tT1GnFnO7KaGDQ8ieO25awSCUso.jpg",
      "cast_id": 28,
      "character": "Young Tull",
      "credit_id": "57af338ec3a36821c6004ff4",
      "order": 15
    },
    {
      "adult": false,
      "gender": 1,
      "id": 1538417,
      "known_for_department": "Acting",
      "name": "Amelia Crouch",
      "original_name": "Amelia Crouch",
      "popularity": 1.7758,
      "profile_path": "/5wsjS144Ca726b6SkhZuE0djOB6.jpg",
      "cast_id": 29,
      "character": "Young Pippa",
      "credit_id": "57af345a9251412f4e007589",
      "order": 16
    },
    {
      "adult": false,
      "gender": 2,
      "id": 60279,
      "known_for_department": "Acting",
      "name": "Fred Tatasciore",
      "original_name": "Fred Tatasciore",
      "popularity": 2.9544,
      "profile_path": "/cKMuclPblMvQ4JQMN0nYKvb5ylu.jpg",
      "cast_id": 30,
      "character": "Mirror Man",
      "credit_id": "57af34b69251410a14005407",
      "order": 17
    },
    {
      "adult": false,
      "gender": 2,
      "id": 202032,
      "known_for_department": "Acting",
      "name": "Ralph Ineson",
      "original_name": "Ralph Ineson",
      "popularity": 3.1636,
      "profile_path": "/sn3ONJw2pJxMHiCqPwvkaiWr5mc.jpg",
      "cast_id": 31,
      "character": "Barkeep",
      "credit_id": "57af350cc3a36878b40060eb",
      "order": 18
    },
    {
      "adult": false,
      "gender": 1,
      "id": 1278497,
      "known_for_department": "Acting",
      "name": "Lynne Wilmot",
      "original_name": "Lynne Wilmot",
      "popularity": 1.3646,
      "profile_path": "/1vZNcMyUcmwXo7UCF5czgN1ms65.jpg",
      "cast_id": 21,
      "character": "Bar Wench",
      "credit_id": "564c9ed4925141594d002089",
      "order": 19
    },
    {
      "adult": false,
      "gender": 2,
      "id": 121606,
      "known_for_department": "Acting",
      "name": "Robert Portal",
      "original_name": "Robert Portal",
      "popularity": 0.6854,
      "profile_path": "/n1HEjfvZrxTShTZ1HncsWJ5Sib7.jpg",
      "cast_id": 32,
      "character": "King",
      "credit_id": "57af3603c3a36803ac002c4b",
      "order": 20
    },
    {
      "adult": false,
      "gender": 2,
      "id": 72313,
      "known_for_department": "Acting",
      "name": "Robert Wilfort",
      "original_name": "Robert Wilfort",
      "popularity": 0.634,
      "profile_path": "/d6cTC4BSzeDIhl8vJ9BM63m2xq5.jpg",
      "cast_id": 33,
      "character": "Nobleman",
      "credit_id": "57af365c9251417319002f21",
      "order": 21
    },
    {
      "adult": false,
      "gender": 2,
      "id": 1619648,
      "known_for_department": "Acting",
      "name": "David Mumeni",
      "original_name": "David Mumeni",
      "popularity": 0.382,
      "profile_path": "/sE7kybwXJoLpKualK5ayWG3U0GM.jpg",
      "cast_id": 34,
      "character": "Lead Soldier",
      "credit_id": "57af36efc3a36803ac002ca9",
      "order": 22
    },
    {
      "adult": false,
      "gender": 1,
      "id": 1347128,
      "known_for_department": "Acting",
      "name": "Kara Lily Hayworth",
      "original_name": "Kara Lily Hayworth",
      "popularity": 0.7519,
      "profile_path": null,
      "cast_id": 35,
      "character": "Freya's Lady in Waiting",
      "credit_id": "57af3847c3a368035900304a",
      "order": 23
    },
    {
      "adult": false,
      "gender": 1,
      "id": 1502431,
      "known_for_department": "Acting",
      "name": "Madeleine Worrall",
      "original_name": "Madeleine Worrall",
      "popularity": 2.4503,
      "profile_path": "/f8TI0MsavCBQaUo6CHqj6ETAB1q.jpg",
      "cast_id": 36,
      "character": "Eric's Mother",
      "credit_id": "57af387d9251410a140055bd",
      "order": 24
    },
    {
      "adult": false,
      "gender": 2,
      "id": 1324655,
      "known_for_department": "Acting",
      "name": "Osi Okerafor",
      "original_name": "Osi Okerafor",
      "popularity": 0.3451,
      "profile_path": "/5cRQplqWztQ0A7EJFQQTzU7cGLZ.jpg",
      "cast_id": 37,
      "character": "Soldier",
      "credit_id": "57af38b2925141731900300d",
      "order": 25
    },
    {
      "adult": false,
      "gender": 2,
      "id": 1682525,
      "known_for_department": "Acting",
      "name": "Ryan Donaldson",
      "original_name": "Ryan Donaldson",
      "popularity": 0.56,
      "profile_path": "/sECqfNPkgCwvgSns9ByzN2CYhD4.jpg",
      "cast_id": 46,
      "character": "Soldier",
      "credit_id": "57e115f3c3a36853e3005706",
      "order": 26
    },
    {
      "adult": false,
      "gender": 2,
      "id": 1662778,
      "known_for_department": "Acting",
      "name": "Chinna Wodu",
      "original_name": "Chinna Wodu",
      "popularity": 0.3456,
      "profile_path": null,
      "cast_id": 38,
      "character": "Huntsman Lookout",
      "credit_id": "57af3951c3a36803730031d0",
      "order": 27
    },
    {
      "adult": false,
      "gender": 2,
      "id": 1626685,
      "known_for_department": "Acting",
      "name": "Andrew Rothney",
      "original_name": "Andrew Rothney",
      "popularity": 1.2614,
      "profile_path": "/i53QqYktqD2OsteTRaIIW8gUQOK.jpg",
      "cast_id": 39,
      "character": "Servant",
      "credit_id": "57af399192514172c9002f7a",
      "order": 28
    },
    {
      "adult": false,
      "gender": 2,
      "id": 1256622,
      "known_for_department": "Acting",
      "name": "Tim Delap",
      "original_name": "Tim Delap",
      "popularity": 0.8119,
      "profile_path": "/qC2DxUkIRdKWQQKF77vEnOjRZgY.jpg",
      "cast_id": 40,
      "character": "Huntsman Guard",
      "credit_id": "57af39fc925141289d004e05",
      "order": 29
    },
    {
      "adult": false,
      "gender": 2,
      "id": 1665609,
      "known_for_department": "Acting",
      "name": "Antony Acheampong",
      "original_name": "Antony Acheampong",
      "popularity": 0.7465,
      "profile_path": "/gD9ns0TbxMdgtFIxfH6Qf7ozKSU.jpg",
      "cast_id": 41,
      "character": "Huntsman #1",
      "credit_id": "57af4354c3a368368b00046d",
      "order": 30
    },
    {
      "adult": false,
      "gender": 2,
      "id": 1665610,
      "known_for_department": "Acting",
      "name": "Ian Davies",
      "original_name": "Ian Davies",
      "popularity": 0.8173,
      "profile_path": "/cPp0fpc1t7F8khdzqzuJOzywBtD.jpg",
      "cast_id": 42,
      "character": "Huntsman #2",
      "credit_id": "57af4449c3a368368b0004de",
      "order": 31
    },
    {
      "adult": false,
      "gender": 2,
      "id": 1665611,
      "known_for_department": "Acting",
      "name": "George Watkins",
      "original_name": "George Watkins",
      "popularity": 0.263,
      "profile_path": null,
      "cast_id": 43,
      "character": "Huntsman #3",
      "credit_id": "57af4569c3a36803ac0032d6",
      "order": 32
    },
    {
      "adult": false,
      "gender": 2,
      "id": 1665612,
      "known_for_department": "Acting",
      "name": "Aj Bediako",
      "original_name": "Aj Bediako",
      "popularity": 0.1834,
      "profile_path": "/ubfQ8FyqWGRucs4lTHPfvk2dmzh.jpg",
      "cast_id": 44,
      "character": "Huntsman #4",
      "credit_id": "57af46bcc3a368368e000604",
      "order": 33
    },
    {
      "adult": false,
      "gender": 1,
      "id": 1682527,
      "known_for_department": "Acting",
      "name": "Maya Wasowicz",
      "original_name": "Maya Wasowicz",
      "popularity": 0.0793,
      "profile_path": null,
      "cast_id": 48,
      "character": "Woman on Cart",
      "credit_id": "57e117a9c3a36853e60052a6",
      "order": 34
    },
    {
      "adult": false,
      "gender": 2,
      "id": 1682524,
      "known_for_department": "Acting",
      "name": "Sam Coulson",
      "original_name": "Sam Coulson",
      "popularity": 0.3397,
      "profile_path": null,
      "cast_id": 45,
      "character": "Snow White Soldier",
      "credit_id": "57e113f1925141045c004f52",
      "order": 35
    },
    {
      "adult": false,
      "gender": 2,
      "id": 1682526,
      "known_for_department": "Acting",
      "name": "Yusuf Hofri",
      "original_name": "Yusuf Hofri",
      "popularity": 0.5025,
      "profile_path": "/lWP3DYPloZ3yxBlTxoDCIoJxHok.jpg",
      "cast_id": 47,
      "character": "Child",
      "credit_id": "57e116e292514104490053dd",
      "order": 36
    },
    {
      "adult": false,
      "gender": 2,
      "id": 1682528,
      "known_for_department": "Acting",
      "name": "Eshan Gopal",
      "original_name": "Eshan Gopal",
      "popularity": 0.2395,
      "profile_path": null,
      "cast_id": 49,
      "character": "Child",
      "credit_id": "57e11903c3a36853e600530f",
      "order": 37
    },
    {
      "adult": false,
      "gender": 0,
      "id": 3150978,
      "known_for_department": "Acting",
      "name": "Annie Guy",
      "original_name": "Annie Guy",
      "popularity": 0.0621,
      "profile_path": null,
      "cast_id": 72,
      "character": "Little Girl",
      "credit_id": "60e7d04c4d6791005e3ecb1f",
      "order": 38
    },
    {
      "adult": false,
      "gender": 0,
      "id": 3150981,
      "known_for_department": "Acting",
      "name": "Natahlia Colbourne",
      "original_name": "Natahlia Colbourne",
      "popularity": 0.0479,
      "profile_path": null,
      "cast_id": 73,
      "character": "Child",
      "credit_id": "60e7d058168ea300749e5ed0",
      "order": 39
    },
    {
      "adult": false,
      "gender": 1,
      "id": 1585960,
      "known_for_department": "Acting",
      "name": "Jadey Duffield",
      "original_name": "Jadey Duffield",
      "popularity": 0.4364,
      "profile_path": "/88x8MbjqwXZSLSFk1nYXCh6Ew1S.jpg",
      "cast_id": 50,
      "character": "Huntswomen (uncredited)",
      "credit_id": "57e119a19251410457005278",
      "order": 40
    },
    {
      "adult": false,
      "gender": 2,
      "id": 3896,
      "known_for_department": "Acting",
      "name": "Liam Neeson",
      "original_name": "Liam Neeson",
      "popularity": 11.0454,
      "profile_path": "/sRLev3wJioBgun3ZoeAUFpkLy0D.jpg",
      "cast_id": 23,
      "character": "Narrator (voice) (uncredited)",
      "credit_id": "5709ac19925141214c001132",
      "order": 41
    },
    {
      "adult": false,
      "gender": 1,
      "id": 37917,
      "known_for_department": "Acting",
      "name": "Kristen Stewart",
      "original_name": "Kristen Stewart",
      "popularity": 5.9845,
      "profile_path": "/ryhCjTGqS6G6OprbR0qUEH355lA.jpg",
      "cast_id": 179,
      "character": "Snow White (archive footage) (uncredited)",
      "credit_id": "6847ae72d374eef39f3fcb47",
      "order": 42
    },
    {
      "adult": false,
      "gender": 2,
      "id": 2860850,
      "known_for_department": "Acting",
      "name": "Karl Farrer",
      "original_name": "Karl Farrer",
      "popularity": 0.5886,
      "profile_path": null,
      "cast_id": 182,
      "character": "Huntsman Instructor (uncredited)",
      "credit_id": "688189a072ce78392c8a5a9b",
      "order": 43
    }
  ],
  "crew": [
    {
      "adult": false,
      "gender": 0,
      "id": 2611279,
      "known_for_department": "Camera",
      "name": "Jack Sands",
      "original_name": "Jack Sands",
      "popularity": 0.192,
      "profile_path": null,
      "credit_id": "6269aa5d12aabc0067ac53f2",
      "department": "Camera",
      "job": "Second Assistant \"C\" Camera"
    },
    {
      "adult": false,
      "gender": 1,
      "id": 2836282,
      "known_for_department": "Camera",
      "name": "Abigail Catto",
      "original_name": "Abigail Catto",
      "popularity": 0.4058,
      "profile_path": null,
      "credit_id": "6269aa0dc613ce005033dbd4",
      "department": "Camera",
      "job": "Second Assistant \"B\" Camera"
    },
    {
      "adult": false,
      "gender": 0,
      "id": 75113,
      "known_for_department": "Camera",
      "name": "Luke Redgrave",
      "original_name": "Luke Redgrave",
      "popularity": 0.8454,
      "profile_path": null,
      "credit_id": "6269aa473876510167e6ce21",
      "department": "Camera",
      "job": "\"B\" Camera Operator"
    },
    {
      "adult": false,
      "gender": 2,
      "id": 1621404,
      "known_for_department": "Camera",
      "name": "Tobias Eedy",
      "original_name": "Tobias Eedy",
      "popularity": 0.3373,
      "profile_path": null,
      "credit_id": "6269aa3364f716160d10823f",
      "department": "Camera",
      "job": "First Assistant \"B\" Camera"
    },
    {
      "adult": false,
      "gender": 2,
      "id": 24232,
      "known_for_department": "Camera",
      "name": "Hamish Doyne-Ditmas",
      "original_name": "Hamish Doyne-Ditmas",
      "popularity": 0.3597,
      "profile_path": null,
      "credit_id": "6269aa1efea0d7006578f7eb",
      "department": "Camera",
      "job": "\"C\" Camera Operator"
    },
    {
      "adult": false,
      "gender": 0,
      "id": 1335552,
      "known_for_department": "Art",
      "name": "Tom Whitehead",
      "original_name": "Tom Whitehead",
      "popularity": 0.3187,
      "profile_path": null,
      "credit_id": "60e7d1276ee3d7007547f194",
      "department": "Art",
      "job": "Art Direction"
    },
    {
      "adult": false,
      "gender": 2,
      "id": 1345597,
      "known_for_department": "Sound",
      "name": "Tobias Poppe",
      "original_name": "Tobias Poppe",
      "popularity": 0.7641,
      "profile_path": "/eWdCqu3yKKWUrNOqAVQxJ29piVC.jpg",
      "credit_id": "60e7d17d8de0ae00469d5b04",
      "department": "Sound",
      "job": "Sound Designer"
    },
    {
      "adult": false,
      "gender": 2,
      "id": 1394131,
      "known_for_department": "Sound",
      "name": "Jon Taylor",
      "original_name": "Jon Taylor",
      "popularity": 0.5582,
      "profile_path": null,
      "credit_id": "60e7d155cee2f6007fba77c3",
      "department": "Sound",
      "job": "Sound Re-Recording Mixer"
    },
    {
      "adult": false,
      "gender": 2,
      "id": 27032,
      "known_for_department": "Art",
      "name": "Dominic Watkins",
      "original_name": "Dominic Watkins",
      "popularity": 0.2838,
      "profile_path": null,
      "credit_id": "60e7cec8cd2046002dc96fd2",
      "department": "Art",
      "job": "Production Design"
    },
    {
      "adult": false,
      "gender": 2,
      "id": 142325,
      "known_for_department": "Crew",
      "name": "Simon Crane",
      "original_name": "Simon Crane",
      "popularity": 0.7401,
      "profile_path": "/9tRVvRYQnHWdh9glTHhgXkkjbHe.jpg",
      "credit_id": "60e7cf66a3b5e600291c3cb4",
      "department": "Directing",
      "job": "Second Unit Director"
    },
    {
      "adult": false,
      "gender": 2,
      "id": 1378695,
      "known_for_department": "Sound",
      "name": "Erik Aadahl",
      "original_name": "Erik Aadahl",
      "popularity": 1.0972,
      "profile_path": "/c02IxbuxyZR93j0gaothnjw1lsZ.jpg",
      "credit_id": "60e7d198bcf8c900480dea3f",
      "department": "Sound",
      "job": "Sound Designer"
    },
    {
      "adult": false,
      "gender": 1,
      "id": 23424,
      "known_for_department": "Production",
      "name": "Lucy Bevan",
      "original_name": "Lucy Bevan",
      "popularity": 0.9662,
      "profile_path": "/hT17FBbxl9gXD5IdieHKoydRcb4.jpg",
      "credit_id": "60e7cef24ca67600750c6d11",
      "department": "Production",
      "job": "Casting"
    },
    {
      "adult": false,
      "gender": 0,
      "id": 2469813,
      "known_for_department": "Directing",
      "name": "Sallie Hard",
      "original_name": "Sallie Hard",
      "popularity": 0.2997,
      "profile_path": null,
      "credit_id": "60e7cf55a3b5e6005d958c16",
      "department": "Directing",
      "job": "Second Assistant Director"
    },
    {
      "adult": false,
      "gender": 1,
      "id": 8386,
      "known_for_department": "Production",
      "name": "Sarah Bradshaw",
      "original_name": "Sarah Bradshaw",
      "popularity": 0.5452,
      "profile_path": null,
      "credit_id": "60e7cf2d168ea30046bb0282",
      "department": "Production",
      "job": "Unit Production Manager"
    },
    {
      "adult": false,
      "gender": 2,
      "id": 1394130,
      "known_for_department": "Sound",
      "name": "Frank A. Montaño",
      "original_name": "Frank A. Montaño",
      "popularity": 1.2563,
      "profile_path": null,
      "credit_id": "60e7d16443250f005f3fcf36",
      "department": "Sound",
      "job": "Sound Re-Recording Mixer"
    },
    {
      "adult": false,
      "gender": 2,
      "id": 10788,
      "known_for_department": "Art",
      "name": "Steven Lawrence",
      "original_name": "Steven Lawrence",
      "popularity": 0.4362,
      "profile_path": null,
      "credit_id": "60e7d0eccee2f6007fba76db",
      "department": "Art",
      "job": "Art Direction"
    },
    {
      "adult": false,
      "gender": 2,
      "id": 10710,
      "known_for_department": "Art",
      "name": "Andrew Ackland-Snow",
      "original_name": "Andrew Ackland-Snow",
      "popularity": 1.0608,
      "profile_path": null,
      "credit_id": "60e7d117a3b5e60074441933",
      "department": "Art",
      "job": "Art Direction"
    },
    {
      "adult": false,
      "gender": 2,
      "id": 11354,
      "known_for_department": "Crew",
      "name": "Ben Cooke",
      "original_name": "Ben Cooke",
      "popularity": 0.6966,
      "profile_path": "/tuMetGw8QNRbWEEtMP3SITwBFc2.jpg",
      "credit_id": "60e7d084df2945005ec9c1ba",
      "department": "Crew",
      "job": "Stunt Coordinator"
    },
    {
      "adult": false,
      "gender": 0,
      "id": 1392627,
      "known_for_department": "Visual Effects",
      "name": "Steve Street",
      "original_name": "Steve Street",
      "popularity": 0.2398,
      "profile_path": null,
      "credit_id": "60e7d0ff4ca6760046297e4b",
      "department": "Crew",
      "job": "Visual Effects Art Director"
    },
    {
      "adult": false,
      "gender": 1,
      "id": 1555170,
      "known_for_department": "Visual Effects",
      "name": "Roma O'Connor",
      "original_name": "Roma O'Connor",
      "popularity": 0.1604,
      "profile_path": null,
      "credit_id": "60e7d09e28723c005d57c03c",
      "department": "Visual Effects",
      "job": "Visual Effects Producer"
    },
    {
      "adult": false,
      "gender": 2,
      "id": 37301,
      "known_for_department": "Art",
      "name": "Frank Walsh",
      "original_name": "Frank Walsh",
      "popularity": 0.3823,
      "profile_path": null,
      "credit_id": "60e7d0c2168ea300247d0417",
      "department": "Art",
      "job": "Supervising Art Director"
    },
    {
      "adult": false,
      "gender": 2,
      "id": 966721,
      "known_for_department": "Art",
      "name": "Dominic Capon",
      "original_name": "Dominic Capon",
      "popularity": 0.3185,
      "profile_path": null,
      "credit_id": "60e7d1434ca676005e1c71f2",
      "department": "Art",
      "job": "Set Decoration"
    },
    {
      "adult": false,
      "gender": 1,
      "id": 1553728,
      "known_for_department": "Production",
      "name": "Simone Goodridge",
      "original_name": "Simone Goodridge",
      "popularity": 0.299,
      "profile_path": null,
      "credit_id": "60e7cf36a3b5e6005d958bdd",
      "department": "Production",
      "job": "Unit Production Manager"
    },
    {
      "adult": false,
      "gender": 2,
      "id": 1190244,
      "known_for_department": "Directing",
      "name": "K.C. Colwell",
      "original_name": "K.C. Colwell",
      "popularity": 0.8929,
      "profile_path": null,
      "credit_id": "60e7cf4acd2046005c63489c",
      "department": "Directing",
      "job": "First Assistant Director"
    },
    {
      "adult": false,
      "gender": 0,
      "id": 422701,
      "known_for_department": "Art",
      "name": "Luigi Marchione",
      "original_name": "Luigi Marchione",
      "popularity": 0.3502,
      "profile_path": null,
      "credit_id": "60e7d10ccd2046005c634d45",
      "department": "Art",
      "job": "Art Direction"
    },
    {
      "adult": false,
      "gender": 2,
      "id": 1378696,
      "known_for_department": "Sound",
      "name": "Ethan Van der Ryn",
      "original_name": "Ethan Van der Ryn",
      "popularity": 2.1773,
      "profile_path": "/cee7w7XpNMSXyFv0F7CtwpBtERB.jpg",
      "credit_id": "60e7d18ddf294500485a56fe",
      "department": "Sound",
      "job": "Sound Designer"
    },
    {
      "adult": false,
      "gender": 2,
      "id": 1982162,
      "known_for_department": "Visual Effects",
      "name": "Paul Lambert",
      "original_name": "Paul Lambert",
      "popularity": 0.5637,
      "profile_path": null,
      "credit_id": "60e7cf0bcee2f6007fba72f2",
      "department": "Visual Effects",
      "job": "Visual Effects Supervisor"
    },
    {
      "adult": false,
      "gender": 2,
      "id": 41848,
      "known_for_department": "Art",
      "name": "John Frankish",
      "original_name": "John Frankish",
      "popularity": 0.3767,
      "profile_path": null,
      "credit_id": "60e7d0e028723c002d54ff77",
      "department": "Art",
      "job": "Art Direction"
    },
    {
      "adult": false,
      "gender": 0,
      "id": 2697966,
      "known_for_department": "Acting",
      "name": "Rudolf Vrba",
      "original_name": "Rudolf Vrba",
      "popularity": 0.3646,
      "profile_path": null,
      "credit_id": "62882ad6d4d509006770de45",
      "department": "Crew",
      "job": "Stunts"
    },
    {
      "adult": false,
      "gender": 2,
      "id": 2175140,
      "known_for_department": "Crew",
      "name": "Tony Smart",
      "original_name": "Tony Smart",
      "popularity": 0.6507,
      "profile_path": null,
      "credit_id": "62882b583dc3130050aa3aa7",
      "department": "Crew",
      "job": "Stunts"
    },
    {
      "adult": false,
      "gender": 2,
      "id": 1891243,
      "known_for_department": "Crew",
      "name": "Erol Ismail",
      "original_name": "Erol Ismail",
      "popularity": 0.5992,
      "profile_path": "/a8rZuQ3dZLgJGW5zWikNkdXBsz.jpg",
      "credit_id": "62882d1ee6357100a8906c95",
      "department": "Crew",
      "job": "Stunts"
    },
    {
      "adult": false,
      "gender": 2,
      "id": 2247105,
      "known_for_department": "Crew",
      "name": "Tomas Ereminas",
      "original_name": "Tomas Ereminas",
      "popularity": 0.7437,
      "profile_path": null,
      "credit_id": "62882dbd1a32481bd52eabed",
      "department": "Crew",
      "job": "Stunts"
    },
    {
      "adult": false,
      "gender": 2,
      "id": 58920,
      "known_for_department": "Crew",
      "name": "Jamie Edgell",
      "original_name": "Jamie Edgell",
      "popularity": 0.4461,
      "profile_path": null,
      "credit_id": "62882de31f3e60009b77a659",
      "department": "Crew",
      "job": "Stunts"
    },
    {
      "adult": false,
      "gender": 1,
      "id": 2148596,
      "known_for_department": "Crew",
      "name": "Maxine Whittaker",
      "original_name": "Maxine Whittaker",
      "popularity": 0.7243,
      "profile_path": null,
      "credit_id": "62882a881a32481bd614dea6",
      "department": "Crew",
      "job": "Stunts"
    },
    {
      "adult": false,
      "gender": 0,
      "id": 237162,
      "known_for_department": "Acting",
      "name": "Greg Townley",
      "original_name": "Greg Townley",
      "popularity": 0.8732,
      "profile_path": "/dqeHjehkLAeztNtVRITviYM8cfF.jpg",
      "credit_id": "62882aff7d5db50050fb1ad7",
      "department": "Crew",
      "job": "Stunts"
    },
    {
      "adult": false,
      "gender": 1,
      "id": 1426477,
      "known_for_department": "Crew",
      "name": "Helen Steinway Bailey",
      "original_name": "Helen Steinway Bailey",
      "popularity": 0.3907,
      "profile_path": null,
      "credit_id": "62882b370d5d853e87f83783",
      "department": "Crew",
      "job": "Stunt Double"
    },
    {
      "adult": false,
      "gender": 1,
      "id": 1426477,
      "known_for_department": "Crew",
      "name": "Helen Steinway Bailey",
      "original_name": "Helen Steinway Bailey",
      "popularity": 0.3907,
      "profile_path": null,
      "credit_id": "62882b462495ab009cbfed51",
      "department": "Crew",
      "job": "Stunts"
    },
    {
      "adult": false,
      "gender": 2,
      "id": 2769359,
      "known_for_department": "Crew",
      "name": "Ben Wright",
      "original_name": "Ben Wright",
      "popularity": 0.4883,
      "profile_path": "/a6buIXOJAVBlZ2OkDVyotEETyn.jpg",
      "credit_id": "62882a218d2f8d00669f89b2",
      "department": "Crew",
      "job": "Stunts"
    },
    {
      "adult": false,
      "gender": 0,
      "id": 29333,
      "known_for_department": "Crew",
      "name": "Roy Taylor",
      "original_name": "Roy Taylor",
      "popularity": 0.6977,
      "profile_path": "/eac87ztd0AcxBLvJPsCoNsvOzVc.jpg",
      "credit_id": "62882b12ec455274c4bf1f94",
      "department": "Crew",
      "job": "Stunts"
    },
    {
      "adult": false,
      "gender": 2,
      "id": 1868623,
      "known_for_department": "Crew",
      "name": "Leo Woodruff",
      "original_name": "Leo Woodruff",
      "popularity": 1.1929,
      "profile_path": null,
      "credit_id": "62882a34e004a600a19ecd0c",
      "department": "Crew",
      "job": "Stunts"
    },
    {
      "adult": false,
      "gender": 2,
      "id": 1233266,
      "known_for_department": "Acting",
      "name": "Andy Wareham",
      "original_name": "Andy Wareham",
      "popularity": 0.6655,
      "profile_path": "/pBqaMoCdnJdgw0M4gQFe1k486Fo.jpg",
      "credit_id": "62882ab17d5db5006696d99a",
      "department": "Crew",
      "job": "Stunts"
    },
    {
      "adult": false,
      "gender": 0,
      "id": 1635036,
      "known_for_department": "Crew",
      "name": "Ricardo Rocca",
      "original_name": "Ricardo Rocca",
      "popularity": 0.2677,
      "profile_path": null,
      "credit_id": "62882baf0d5d853e85874546",
      "department": "Crew",
      "job": "Stunts"
    },
    {
      "adult": false,
      "gender": 2,
      "id": 1878829,
      "known_for_department": "Acting",
      "name": "Jimmy Pethrus",
      "original_name": "Jimmy Pethrus",
      "popularity": 0.1653,
      "profile_path": "/9H4MI0g4tFTkJ8ZwHs4zlMLEr5.jpg",
      "credit_id": "62882c2f1a32481bd771adf3",
      "department": "Crew",
      "job": "Stunts"
    },
    {
      "adult": false,
      "gender": 1,
      "id": 2309181,
      "known_for_department": "Crew",
      "name": "Carly Michaels",
      "original_name": "Carly Michaels",
      "popularity": 0.2308,
      "profile_path": null,
      "credit_id": "62882c586c84920065bbfc33",
      "department": "Crew",
      "job": "Stunts"
    },
    {
      "adult": false,
      "gender": 2,
      "id": 2208934,
      "known_for_department": "Crew",
      "name": "Mark Archer",
      "original_name": "Mark Archer",
      "popularity": 0.2853,
      "profile_path": "/ozj8zq3crSY4hJktS6iSAJ7bFm8.jpg",
      "credit_id": "62882eb3d4d5090051966948",
      "department": "Crew",
      "job": "Stunts"
    },
    {
      "adult": false,
      "gender": 2,
      "id": 1766731,
      "known_for_department": "Crew",
      "name": "William Willoughby",
      "original_name": "William Willoughby",
      "popularity": 0.3921,
      "profile_path": "/mbxpsBKkhmRpSQZckfMAL6S6Er0.jpg",
      "credit_id": "62882a630d5d853e87f8340f",
      "department": "Crew",
      "job": "Stunts"
    },
    {
      "adult": false,
      "gender": 2,
      "id": 2151822,
      "known_for_department": "Crew",
      "name": "Marlow Warrington-Mattei",
      "original_name": "Marlow Warrington-Mattei",
      "popularity": 0.4244,
      "profile_path": "/zOhoccw9tmETCW9NpipREXToFAz.jpg",
      "credit_id": "62882a9bec455274c4bf1e51",
      "department": "Crew",
      "job": "Stunts"
    },
    {
      "adult": false,
      "gender": 2,
      "id": 2441229,
      "known_for_department": "Crew",
      "name": "Oleg Podobin",
      "original_name": "Oleg Podobin",
      "popularity": 1.5571,
      "profile_path": null,
      "credit_id": "62882c190859b451c9a93402",
      "department": "Crew",
      "job": "Stunts"
    },
    {
      "adult": false,
      "gender": 2,
      "id": 1795844,
      "known_for_department": "Crew",
      "name": "Mens-Sana Tamakloe",
      "original_name": "Mens-Sana Tamakloe",
      "popularity": 0.2244,
      "profile_path": "/vhQItWQP3CgfExntxGhCHat2Tlq.jpg",
      "credit_id": "62882b247e403d005036ef12",
      "department": "Crew",
      "job": "Stunts"
    },
    {
      "adult": false,
      "gender": 1,
      "id": 2151824,
      "known_for_department": "Crew",
      "name": "Annabel Wood",
      "original_name": "Annabel Wood",
      "popularity": 0.493,
      "profile_path": "/4CHKGGBERzaTL3I2NkB4a4w4v9p.jpg",
      "credit_id": "62882a49e635710068bec0ce",
      "department": "Crew",
      "job": "Stunts"
    },
    {
      "adult": false,
      "gender": 1,
      "id": 2143663,
      "known_for_department": "Crew",
      "name": "Donna Williams",
      "original_name": "Donna Williams",
      "popularity": 0.2592,
      "profile_path": null,
      "credit_id": "62882a768d2f8d009ce308bc",
      "department": "Crew",
      "job": "Stunts"
    },
    {
      "adult": false,
      "gender": 2,
      "id": 1205740,
      "known_for_department": "Directing",
      "name": "Damien Walters",
      "original_name": "Damien Walters",
      "popularity": 0.6146,
      "profile_path": "/sQ72u2WqvUtEvHYDT1iz5KSgSvY.jpg",
      "credit_id": "62882ac3e004a600506fe714",
      "department": "Crew",
      "job": "Stunts"
    },
    {
      "adult": false,
      "gender": 2,
      "id": 2441230,
      "known_for_department": "Crew",
      "name": "Edward Upcott",
      "original_name": "Edward Upcott",
      "popularity": 0.2775,
      "profile_path": "/fxwCWvxIEOmtVNxRG2W1fqPDAWv.jpg",
      "credit_id": "62882ae91a32481bd52e9e88",
      "department": "Crew",
      "job": "Stunts"
    },
    {
      "adult": false,
      "gender": 2,
      "id": 1760899,
      "known_for_department": "Crew",
      "name": "Ian Kay",
      "original_name": "Ian Kay",
      "popularity": 0.4244,
      "profile_path": "/vPNsIjcFhf9I7UfKxxBfT7rmVU6.jpg",
      "credit_id": "62882d0cd1a8930050dee3e8",
      "department": "Crew",
      "job": "Stunts"
    },
    {
      "adult": false,
      "gender": 2,
      "id": 1727816,
      "known_for_department": "Crew",
      "name": "Danny Euston",
      "original_name": "Danny Euston",
      "popularity": 0.3163,
      "profile_path": "/51LIMbwX2uGJqtE67c2b8of6WAT.jpg",
      "credit_id": "62882daae6357100a8907025",
      "department": "Crew",
      "job": "Stunts"
    },
    {
      "adult": false,
      "gender": 2,
      "id": 1278128,
      "known_for_department": "Crew",
      "name": "Luke Scott",
      "original_name": "Luke Scott",
      "popularity": 0.5249,
      "profile_path": "/aOuKuY9DAQnNd5sLZUQcNq9xhsz.jpg",
      "credit_id": "62882b847e403d00669586c9",
      "department": "Crew",
      "job": "Stunts"
    },
    {
      "adult": false,
      "gender": 2,
      "id": 1280236,
      "known_for_department": "Crew",
      "name": "Kai Martin",
      "original_name": "Kai Martin",
      "popularity": 1.108,
      "profile_path": "/5MrWmhROEY7U4PU66mbTEmjeAt5.jpg",
      "credit_id": "62882cb67d5db50099d28cfd",
      "department": "Crew",
      "job": "Stunts"
    },
    {
      "adult": false,
      "gender": 2,
      "id": 7052,
      "known_for_department": "Crew",
      "name": "Adam Kirley",
      "original_name": "Adam Kirley",
      "popularity": 0.7138,
      "profile_path": "/5zsQgn1asesY2PYqKpJf0gi1Z4d.jpg",
      "credit_id": "62882ce66c8492009d12b573",
      "department": "Crew",
      "job": "Stunts"
    },
    {
      "adult": false,
      "gender": 2,
      "id": 2151841,
      "known_for_department": "Crew",
      "name": "Oliver Gough",
      "original_name": "Oliver Gough",
      "popularity": 0.2258,
      "profile_path": "/w0uIFnIqyqlUXj4H6i4wOmIRWKs.jpg",
      "credit_id": "62882d583dc313009addf51b",
      "department": "Crew",
      "job": "Stunts"
    },
    {
      "adult": false,
      "gender": 2,
      "id": 2095537,
      "known_for_department": "Crew",
      "name": "Clint Elvy",
      "original_name": "Clint Elvy",
      "popularity": 0.2009,
      "profile_path": null,
      "credit_id": "62882dd01a32481bd52eac53",
      "department": "Crew",
      "job": "Stunts"
    },
    {
      "adult": false,
      "gender": 2,
      "id": 1912842,
      "known_for_department": "Crew",
      "name": "Lee Bagley",
      "original_name": "Lee Bagley",
      "popularity": 0.574,
      "profile_path": null,
      "credit_id": "62882e97e004a600661256e3",
      "department": "Crew",
      "job": "Stunts"
    },
    {
      "adult": false,
      "gender": 0,
      "id": 1444646,
      "known_for_department": "Crew",
      "name": "Stanislav Satko",
      "original_name": "Stanislav Satko",
      "popularity": 1.2096,
      "profile_path": null,
      "credit_id": "62882b9b6c84920050b592b0",
      "department": "Crew",
      "job": "Stunts"
    },
    {
      "adult": false,
      "gender": 0,
      "id": 2770596,
      "known_for_department": "Crew",
      "name": "Zach Roberts",
      "original_name": "Zach Roberts",
      "popularity": 0.3167,
      "profile_path": null,
      "credit_id": "62882bdf2495ab004f924acc",
      "department": "Crew",
      "job": "Stunts"
    },
    {
      "adult": false,
      "gender": 2,
      "id": 1121204,
      "known_for_department": "Crew",
      "name": "David Garrick",
      "original_name": "David Garrick",
      "popularity": 0.5258,
      "profile_path": "/pEXvS6ze6bKAYuM4EHxDeTXYEw.jpg",
      "credit_id": "62882d6fe004a600a19ede15",
      "department": "Crew",
      "job": "Stunts"
    },
    {
      "adult": false,
      "gender": 2,
      "id": 1405566,
      "known_for_department": "Crew",
      "name": "Douglas Robson",
      "original_name": "Douglas Robson",
      "popularity": 1.5081,
      "profile_path": "/A7dwhMhzmpk0o6tPW16ePZRaLjo.jpg",
      "credit_id": "62882bcc6c84920065bbf8ef",
      "department": "Crew",
      "job": "Stunts"
    },
    {
      "adult": false,
      "gender": 1,
      "id": 2752045,
      "known_for_department": "Crew",
      "name": "Tilly Powell",
      "original_name": "Tilly Powell",
      "popularity": 0.4679,
      "profile_path": null,
      "credit_id": "62882c071a32481bd614e53c",
      "department": "Crew",
      "job": "Stunts"
    },
    {
      "adult": false,
      "gender": 2,
      "id": 1157595,
      "known_for_department": "Acting",
      "name": "Nick McKinless",
      "original_name": "Nick McKinless",
      "popularity": 1.4443,
      "profile_path": "/7EE9cDfjV0eAHhGyeIQOOw4UEZK.jpg",
      "credit_id": "62882c6ae004a600a19ed84e",
      "department": "Crew",
      "job": "Stunts"
    },
    {
      "adult": false,
      "gender": 1,
      "id": 1251918,
      "known_for_department": "Crew",
      "name": "Rachelle Beinart",
      "original_name": "Rachelle Beinart",
      "popularity": 0.6587,
      "profile_path": "/jFOg0rcIBokXUUbIEWNZrSKopsz.jpg",
      "credit_id": "62882e70d1a8930050deec79",
      "department": "Crew",
      "job": "Stunts"
    },
    {
      "adult": false,
      "gender": 2,
      "id": 1381548,
      "known_for_department": "Crew",
      "name": "Bobby Holland Hanton",
      "original_name": "Bobby Holland Hanton",
      "popularity": 0.4357,
      "profile_path": "/qoAkLDUn43DhnyKv5uf0UGXJzpz.jpg",
      "credit_id": "62882d33ec455274c360dc90",
      "department": "Crew",
      "job": "Stunt Double"
    },
    {
      "adult": false,
      "gender": 0,
      "id": 2527063,
      "known_for_department": "Crew",
      "name": "Adam Brashaw",
      "original_name": "Adam Brashaw",
      "popularity": 0.2627,
      "profile_path": null,
      "credit_id": "62882e5ee004a6006612557e",
      "department": "Crew",
      "job": "Stunts"
    },
    {
      "adult": false,
      "gender": 0,
      "id": 2143648,
      "known_for_department": "Crew",
      "name": "Chris Newton",
      "original_name": "Chris Newton",
      "popularity": 0.1811,
      "profile_path": null,
      "credit_id": "62882c42ec455274c2888ccb",
      "department": "Crew",
      "job": "Stunts"
    },
    {
      "adult": false,
      "gender": 2,
      "id": 1074616,
      "known_for_department": "Acting",
      "name": "Vladimir \"Furdo\" Furdik",
      "original_name": "Vladimir \"Furdo\" Furdik",
      "popularity": 1.0865,
      "profile_path": "/1661o64vCOQyFMswIMZBB3MsOb8.jpg",
      "credit_id": "62882d838d2f8d005148f51f",
      "department": "Crew",
      "job": "Stunts"
    },
    {
      "adult": false,
      "gender": 2,
      "id": 2770611,
      "known_for_department": "Crew",
      "name": "Bogdan Kumšackij",
      "original_name": "Bogdan Kumšackij",
      "popularity": 0.5498,
      "profile_path": "/bJSkpkpRSbb7DgIVovxKu2cagN6.jpg",
      "credit_id": "62882cd25cea180067dee837",
      "department": "Crew",
      "job": "Stunts"
    },
    {
      "adult": false,
      "gender": 2,
      "id": 2228384,
      "known_for_department": "Crew",
      "name": "David R. Grant",
      "original_name": "David R. Grant",
      "popularity": 0.5626,
      "profile_path": "/scEs9nXx4OXPPnnnwZwNTV38U5g.jpg",
      "credit_id": "62882d463dc31300666c8521",
      "department": "Crew",
      "job": "Stunts"
    },
    {
      "adult": false,
      "gender": 2,
      "id": 1849452,
      "known_for_department": "Crew",
      "name": "Tony Christian",
      "original_name": "Tony Christian",
      "popularity": 0.4561,
      "profile_path": "/vQNmZWh5msxjOYbSn5ZkPVajfgF.jpg",
      "credit_id": "62882e398d2f8d00669f9f7c",
      "department": "Crew",
      "job": "Stunts"
    },
    {
      "adult": false,
      "gender": 2,
      "id": 2815382,
      "known_for_department": "Acting",
      "name": "Joseph Baxter",
      "original_name": "Joseph Baxter",
      "popularity": 0.0844,
      "profile_path": null,
      "credit_id": "62882e843dc31300666c8d03",
      "department": "Crew",
      "job": "Stunts"
    },
    {
      "adult": false,
      "gender": 1,
      "id": 66164,
      "known_for_department": "Acting",
      "name": "Cecily Fay",
      "original_name": "Cecily Fay",
      "popularity": 1.7642,
      "profile_path": "/7o0LjsXXi01Zsyb8fvAouM9xESu.jpg",
      "credit_id": "62882d960d5d853e85875176",
      "department": "Crew",
      "job": "Stunts"
    },
    {
      "adult": false,
      "gender": 0,
      "id": 3544421,
      "known_for_department": "Crew",
      "name": "David Collom",
      "original_name": "David Collom",
      "popularity": 0.1412,
      "profile_path": null,
      "credit_id": "62882e236c8492009d12bc64",
      "department": "Crew",
      "job": "Stunts"
    },
    {
      "adult": false,
      "gender": 0,
      "id": 3131374,
      "known_for_department": "Crew",
      "name": "Dom Dumaresq",
      "original_name": "Dom Dumaresq",
      "popularity": 0.3307,
      "profile_path": null,
      "credit_id": "62882df9d4d50900519665a7",
      "department": "Crew",
      "job": "Stunts"
    },
    {
      "adult": false,
      "gender": 1,
      "id": 237411,
      "known_for_department": "Crew",
      "name": "Nellie Burroughes",
      "original_name": "Nellie Burroughes",
      "popularity": 0.5214,
      "profile_path": "/A3gOCRPDKIZQpiVddbEwCokr5na.jpg",
      "credit_id": "62882e4bf10a1a33ab2c177e",
      "department": "Crew",
      "job": "Stunts"
    },
    {
      "adult": false,
      "gender": 2,
      "id": 2285056,
      "known_for_department": "Crew",
      "name": "Sina Ali",
      "original_name": "Sina Ali",
      "popularity": 1.452,
      "profile_path": null,
      "credit_id": "62882ec92495ab004f925dad",
      "department": "Crew",
      "job": "Stunts"
    },
    {
      "adult": false,
      "gender": 2,
      "id": 3582744,
      "known_for_department": "Crew",
      "name": "Matt Crook",
      "original_name": "Matt Crook",
      "popularity": 0.3798,
      "profile_path": "/eNWljUxiYjbIpQ1HwraCOsk44XB.jpg",
      "credit_id": "62a28edf7e12f06e06bd638c",
      "department": "Crew",
      "job": "Stunts"
    },
    {
      "adult": false,
      "gender": 2,
      "id": 18311,
      "known_for_department": "Production",
      "name": "Joe Roth",
      "original_name": "Joe Roth",
      "popularity": 0.6513,
      "profile_path": "/xLWXgnO7f3298NQawL9ctjA1uUZ.jpg",
      "credit_id": "552f5e9292514136ed001d06",
      "department": "Production",
      "job": "Producer"
    },
    {
      "adult": false,
      "gender": 2,
      "id": 432,
      "known_for_department": "Camera",
      "name": "Phedon Papamichael",
      "original_name": "Phedon Papamichael",
      "popularity": 0.4472,
      "profile_path": "/ht21oUPCRZk42fFzAH14S9dG3tq.jpg",
      "credit_id": "552f5e52c3a3686be2005716",
      "department": "Camera",
      "job": "Director of Photography"
    },
    {
      "adult": false,
      "gender": 2,
      "id": 1454884,
      "known_for_department": "Visual Effects",
      "name": "Cedric Nicolas-Troyan",
      "original_name": "Cedric Nicolas-Troyan",
      "popularity": 1.3586,
      "profile_path": "/e5r1BokTOBfCSaAJd69whUTTGOT.jpg",
      "credit_id": "552f5dd59251413b3b002be0",
      "department": "Directing",
      "job": "Director"
    },
    {
      "adult": false,
      "gender": 2,
      "id": 1213,
      "known_for_department": "Sound",
      "name": "James Newton Howard",
      "original_name": "James Newton Howard",
      "popularity": 1.1831,
      "profile_path": "/qB4JgzCXCjr7NwW7UNrgBrWZDlo.jpg",
      "credit_id": "640b9961724de10083bf6514",
      "department": "Sound",
      "job": "Original Music Composer"
    },
    {
      "adult": false,
      "gender": 2,
      "id": 228135,
      "known_for_department": "Writing",
      "name": "Evan Daugherty",
      "original_name": "Evan Daugherty",
      "popularity": 0.617,
      "profile_path": "/gyZAjiCCf2ujWzQZLLAA2Enag3R.jpg",
      "credit_id": "59a5c042c3a3684025010419",
      "department": "Writing",
      "job": "Characters"
    },
    {
      "adult": false,
      "gender": 2,
      "id": 35796,
      "known_for_department": "Writing",
      "name": "Craig Mazin",
      "original_name": "Craig Mazin",
      "popularity": 1.3504,
      "profile_path": "/uEhna6qcMuyU5TP7irpTUZ2ZsZc.jpg",
      "credit_id": "6448099e140bad04d3a77cec",
      "department": "Writing",
      "job": "Writer"
    },
    {
      "adult": false,
      "gender": 0,
      "id": 1842148,
      "known_for_department": "Sound",
      "name": "Justin M. Davey",
      "original_name": "Justin M. Davey",
      "popularity": 0.6249,
      "profile_path": null,
      "credit_id": "64480f2c140bad04fda7804c",
      "department": "Sound",
      "job": "Sound Effects Editor"
    },
    {
      "adult": false,
      "gender": 2,
      "id": 80675,
      "known_for_department": "Writing",
      "name": "Evan Spiliotopoulos",
      "original_name": "Evan Spiliotopoulos",
      "popularity": 0.6326,
      "profile_path": "/cznBeImhZFRIcRBKHo99nAdf1zJ.jpg",
      "credit_id": "644809adce997a04b9872d5a",
      "department": "Writing",
      "job": "Writer"
    },
    {
      "adult": false,
      "gender": 1,
      "id": 557,
      "known_for_department": "Costume & Make-Up",
      "name": "Colleen Atwood",
      "original_name": "Colleen Atwood",
      "popularity": 0.7925,
      "profile_path": "/2jN2s8K3SP9lecU7fF3IxvmEZ6W.jpg",
      "credit_id": "64480b6ec51acd0566a950f5",
      "department": "Costume & Make-Up",
      "job": "Costume Design"
    },
    {
      "adult": false,
      "gender": 2,
      "id": 76593,
      "known_for_department": "Camera",
      "name": "Giles Keyte",
      "original_name": "Giles Keyte",
      "popularity": 0.5268,
      "profile_path": null,
      "credit_id": "64480ebc140bad047fa78026",
      "department": "Camera",
      "job": "Still Photographer"
    },
    {
      "adult": false,
      "gender": 2,
      "id": 1387183,
      "known_for_department": "Sound",
      "name": "John C. Stuver",
      "original_name": "John C. Stuver",
      "popularity": 1.6801,
      "profile_path": null,
      "credit_id": "64480f39b76cbb0492a3ae3b",
      "department": "Sound",
      "job": "Dialogue Editor"
    },
    {
      "adult": false,
      "gender": 2,
      "id": 1658269,
      "known_for_department": "Sound",
      "name": "Steve Finn",
      "original_name": "Steve Finn",
      "popularity": 0.2004,
      "profile_path": null,
      "credit_id": "64480ddf6e938a04a43e7f1f",
      "department": "Sound",
      "job": "Boom Operator"
    },
    {
      "adult": false,
      "gender": 2,
      "id": 1345597,
      "known_for_department": "Sound",
      "name": "Tobias Poppe",
      "original_name": "Tobias Poppe",
      "popularity": 0.7641,
      "profile_path": "/eWdCqu3yKKWUrNOqAVQxJ29piVC.jpg",
      "credit_id": "64480d15b76cbb04e6a3ad0c",
      "department": "Sound",
      "job": "Supervising Sound Editor"
    },
    {
      "adult": false,
      "gender": 1,
      "id": 1404875,
      "known_for_department": "Directing",
      "name": "Jo Beckett",
      "original_name": "Jo Beckett",
      "popularity": 0.4669,
      "profile_path": null,
      "credit_id": "64480e7bce997a050d872f40",
      "department": "Directing",
      "job": "Script Supervisor"
    },
    {
      "adult": false,
      "gender": 2,
      "id": 1357059,
      "known_for_department": "Sound",
      "name": "David V. Butler",
      "original_name": "David V. Butler",
      "popularity": 0.9889,
      "profile_path": null,
      "credit_id": "64480ef96e938a04a43e7fb3",
      "department": "Sound",
      "job": "Supervising ADR Editor"
    },
    {
      "adult": false,
      "gender": 0,
      "id": 1338482,
      "known_for_department": "Sound",
      "name": "Chris Diebold",
      "original_name": "Chris Diebold",
      "popularity": 0.5228,
      "profile_path": null,
      "credit_id": "64480f196e938a04d03e7f3e",
      "department": "Sound",
      "job": "Sound Effects Editor"
    },
    {
      "adult": false,
      "gender": 2,
      "id": 105780,
      "known_for_department": "Sound",
      "name": "Chris Munro",
      "original_name": "Chris Munro",
      "popularity": 0.524,
      "profile_path": "/xfuQraRSxQNwgKyrY47FLeoVB4z.jpg",
      "credit_id": "64480d99f04d01038597e00c",
      "department": "Sound",
      "job": "Sound Mixer"
    },
    {
      "adult": false,
      "gender": 2,
      "id": 1357059,
      "known_for_department": "Sound",
      "name": "David V. Butler",
      "original_name": "David V. Butler",
      "popularity": 0.9889,
      "profile_path": null,
      "credit_id": "64480f043dc3130473dac429",
      "department": "Sound",
      "job": "Supervising Dialogue Editor"
    },
    {
      "adult": false,
      "gender": 2,
      "id": 1737656,
      "known_for_department": "Sound",
      "name": "Jonathan Klein",
      "original_name": "Jonathan Klein",
      "popularity": 0.4876,
      "profile_path": null,
      "credit_id": "64480ede6e938a02fd3e7f04",
      "department": "Sound",
      "job": "Foley Supervisor"
    },
    {
      "adult": false,
      "gender": 2,
      "id": 1334458,
      "known_for_department": "Art",
      "name": "David Cheesman",
      "original_name": "David Cheesman",
      "popularity": 0.2229,
      "profile_path": null,
      "credit_id": "64480d49ce997a04e3872eed",
      "department": "Art",
      "job": "Property Master"
    },
    {
      "adult": false,
      "gender": 2,
      "id": 1645047,
      "known_for_department": "Crew",
      "name": "Liang Yang",
      "original_name": "Liang Yang",
      "popularity": 1.0652,
      "profile_path": "/z6UgXBqpbrrwikfJkeFoSvFUzqu.jpg",
      "credit_id": "5a2f84b7925141032c173307",
      "department": "Crew",
      "job": "Stunts"
    },
    {
      "adult": false,
      "gender": 1,
      "id": 1337357,
      "known_for_department": "Art",
      "name": "Elo Soode",
      "original_name": "Elo Soode",
      "popularity": 0.4025,
      "profile_path": null,
      "credit_id": "644f91122fccee0302ce0c9b",
      "department": "Art",
      "job": "Concept Artist"
    },
    {
      "adult": false,
      "gender": 1,
      "id": 1337357,
      "known_for_department": "Art",
      "name": "Elo Soode",
      "original_name": "Elo Soode",
      "popularity": 0.4025,
      "profile_path": null,
      "credit_id": "64956d4fd5ffcb00ad84ee5d",
      "department": "Art",
      "job": "Conceptual Design"
    },
    {
      "adult": false,
      "gender": 2,
      "id": 898,
      "known_for_department": "Editing",
      "name": "Mark Goldblatt",
      "original_name": "Mark Goldblatt",
      "popularity": 1.0919,
      "profile_path": "/9PuP0ma2BGgDyuauMQ9weWNk4t7.jpg",
      "credit_id": "5bce4f3d0e0a265d4400735b",
      "department": "Editing",
      "job": "Additional Editor"
    },
    {
      "adult": false,
      "gender": 2,
      "id": 3987,
      "known_for_department": "Editing",
      "name": "Conrad Buff IV",
      "original_name": "Conrad Buff IV",
      "popularity": 1.5532,
      "profile_path": null,
      "credit_id": "5bce4f54c3a3683d6900708c",
      "department": "Editing",
      "job": "Editor"
    },
    {
      "adult": false,
      "gender": 2,
      "id": 928399,
      "known_for_department": "Production",
      "name": "Palak Patel",
      "original_name": "Palak Patel",
      "popularity": 0.415,
      "profile_path": null,
      "credit_id": "5bce4f6ac3a3683d6900709b",
      "department": "Production",
      "job": "Executive Producer"
    },
    {
      "adult": false,
      "gender": 1,
      "id": 8386,
      "known_for_department": "Production",
      "name": "Sarah Bradshaw",
      "original_name": "Sarah Bradshaw",
      "popularity": 0.5452,
      "profile_path": null,
      "credit_id": "5bce4f70c3a3683d63007920",
      "department": "Production",
      "job": "Executive Producer"
    },
    {
      "adult": false,
      "gender": 0,
      "id": 1537541,
      "known_for_department": "Visual Effects",
      "name": "Lynda Thompson",
      "original_name": "Lynda Thompson",
      "popularity": 0.3684,
      "profile_path": null,
      "credit_id": "5bce4f7bc3a3683d6f006bac",
      "department": "Production",
      "job": "Associate Producer"
    },
    {
      "adult": false,
      "gender": 2,
      "id": 1050634,
      "known_for_department": "Art",
      "name": "James Lewis",
      "original_name": "James Lewis",
      "popularity": 0.3823,
      "profile_path": null,
      "credit_id": "5dda630b0cd4460019299bae",
      "department": "Art",
      "job": "Art Direction"
    },
    {
      "adult": false,
      "gender": 1,
      "id": 2607303,
      "known_for_department": "Directing",
      "name": "Carolina Jiménez",
      "original_name": "Carolina Jiménez",
      "popularity": 1.6908,
      "profile_path": "/3GiT1cIGLb5XpuQmydHHscGcHFb.jpg",
      "credit_id": "5eb832c2cc277c00206b9456",
      "department": "Directing",
      "job": "Layout"
    },
    {
      "adult": false,
      "gender": 2,
      "id": 1882061,
      "known_for_department": "Lighting",
      "name": "Derek Hoffman",
      "original_name": "Derek Hoffman",
      "popularity": 0.2001,
      "profile_path": null,
      "credit_id": "5f98d42343999b0038fb337a",
      "department": "Lighting",
      "job": "Lighting Programmer"
    },
    {
      "adult": false,
      "gender": 2,
      "id": 1428918,
      "known_for_department": "Camera",
      "name": "Olly Tellett",
      "original_name": "Olly Tellett",
      "popularity": 0.4726,
      "profile_path": null,
      "credit_id": "671455e7d5b7926e946ff086",
      "department": "Camera",
      "job": "First Assistant \"A\" Camera"
    },
    {
      "adult": false,
      "gender": 2,
      "id": 2659269,
      "known_for_department": "Directing",
      "name": "Donald E G Bentley",
      "original_name": "Donald E G Bentley",
      "popularity": 0.2902,
      "profile_path": "/o9i2OiiI4onJJYLObxalp2VHsS9.jpg",
      "credit_id": "67bb7d65286bde3a090a6d34",
      "department": "Production",
      "job": "Key Set Production Assistant"
    },
    {
      "adult": false,
      "gender": 2,
      "id": 1560110,
      "known_for_department": "Editing",
      "name": "Michael Hatzer",
      "original_name": "Michael Hatzer",
      "popularity": 0.7235,
      "profile_path": null,
      "credit_id": "67e06b04f6a0fcbd004db9e6",
      "department": "Editing",
      "job": "Digital Colorist"
    },
    {
      "adult": false,
      "gender": 0,
      "id": 3162983,
      "known_for_department": "Production",
      "name": "Michael Mann",
      "original_name": "Michael Mann",
      "popularity": 0.1825,
      "profile_path": null,
      "credit_id": "67e8ef147a75294b76c697b7",
      "department": "Production",
      "job": "Production Coordinator"
    },
    {
      "adult": false,
      "gender": 2,
      "id": 1405198,
      "known_for_department": "Lighting",
      "name": "David Sinfield",
      "original_name": "David Sinfield",
      "popularity": 0.2787,
      "profile_path": null,
      "credit_id": "6802f827e4753425efad5958",
      "department": "Lighting",
      "job": "Gaffer"
    },
    {
      "adult": false,
      "gender": 2,
      "id": 1480629,
      "known_for_department": "Costume & Make-Up",
      "name": "Luca Vannella",
      "original_name": "Luca Vannella",
      "popularity": 0.3339,
      "profile_path": "/3V95IInYtScu9PkCdc4YwHWP2SH.jpg",
      "credit_id": "681a70bdf45092c3f3e1a50e",
      "department": "Costume & Make-Up",
      "job": "Hair Designer"
    },
    {
      "adult": false,
      "gender": 2,
      "id": 1480629,
      "known_for_department": "Costume & Make-Up",
      "name": "Luca Vannella",
      "original_name": "Luca Vannella",
      "popularity": 0.3339,
      "profile_path": "/3V95IInYtScu9PkCdc4YwHWP2SH.jpg",
      "credit_id": "681a70c4b940a3393d21d824",
      "department": "Costume & Make-Up",
      "job": "Makeup Designer"
    },
    {
      "adult": false,
      "gender": 2,
      "id": 1545988,
      "known_for_department": "Visual Effects",
      "name": "Dominic Tuohy",
      "original_name": "Dominic Tuohy",
      "popularity": 1.1256,
      "profile_path": "/m3aqlLcspitKRkwNzbYWTmFys6c.jpg",
      "credit_id": "6829efbbef6883779bf5580d",
      "department": "Visual Effects",
      "job": "Special Effects Supervisor"
    },
    {
      "adult": false,
      "gender": 1,
      "id": 2143600,
      "known_for_department": "Art",
      "name": "Tracey Wilson",
      "original_name": "Tracey Wilson",
      "popularity": 0.7243,
      "profile_path": null,
      "credit_id": "68540a7f7dbded029c550565",
      "department": "Art",
      "job": "Storyboard Artist"
    },
    {
      "adult": false,
      "gender": 2,
      "id": 937946,
      "known_for_department": "Camera",
      "name": "Peter Field",
      "original_name": "Peter Field",
      "popularity": 0.7425,
      "profile_path": "/wHPNA7507ff8GE4Zi6vZLJvHLNa.jpg",
      "credit_id": "687ed9e0bf9903a48bf76ec8",
      "department": "Camera",
      "job": "Camera Operator"
    },
    {
      "adult": false,
      "gender": 1,
      "id": 23490,
      "known_for_department": "Art",
      "name": "Julia Dehoff",
      "original_name": "Julia Dehoff",
      "popularity": 0.4504,
      "profile_path": null,
      "credit_id": "68d52e6cc803f851efa2bebf",
      "department": "Art",
      "job": "Assistant Art Director"
    },
    {
      "adult": false,
      "gender": 2,
      "id": 2086121,
      "known_for_department": "Camera",
      "name": "Paul Snell",
      "original_name": "Paul Snell",
      "popularity": 0.3103,
      "profile_path": null,
      "credit_id": "6900f7f5d7160be0de2ab3f1",
      "department": "Camera",
      "job": "Second Assistant \"A\" Camera"
    }
  ]
}