{"actorId":18997,"neighbors":[{"actorId":14592,"movies":[{"id":135397,"title":"Jurassic World","poster":null,"pop":15.1},{"id":507086,"title":"Jurassic World Dominion","poster":null,"pop":14.9},{"id":351286,"title":"Jurassic World: Fallen Kingdom","poster":null,"pop":12.1}]},{"actorId":73457,"movies":[{"id":135397,"title":"Jurassic World","poster":null,"pop":15.1},{"id":507086,"title":"Jurassic World Dominion","poster":null,"pop":14.9},{"id":351286,"title":"Jurassic World: Fallen Kingdom","poster":null,"pop":12.1}]},{"actorId":20582,"movies":[{"id":135397,"title":"Jurassic World","poster":null,"pop":15.1},{"id":559,"title":"Spider-Man 3","poster":null,"pop":13.8},{"id":534,"title":"Terminator Salvation","poster":null,"pop":8.8}]},{"actorId":2505,"movies":[{"id":559,"title":"Spider-Man 3","poster":null,"pop":13.8},{"id":351286,"title":"Jurassic World: Fallen Kingdom","poster":null,"pop":12.1}]},{"actorId":1029934,"movies":[{"id":507086,"title":"Jurassic World Dominion","poster":null,"pop":14.9},{"id":351286,"title":"Jurassic World: Fallen Kingdom","poster":null,"pop":12.1}]},{"actorId":78423,"movies":[{"id":135397,"title":"Jurassic World","poster":null,"pop":15.1},{"id":507086,"title":"Jurassic World Dominion","poster":null,"pop":14.9}]},{"actorId":84223,"movies":[{"id":24021,"title":"The Twilight Saga: Eclipse","poster":null,"pop":9.4},{"id":40807,"title":"50/50","poster":null,"pop":5.1}]},{"actorId":85419,"movies":[{"id":534,"title":"Terminator Salvation","poster":null,"pop":8.8},{"id":334524,"title":"Gold","poster":null,"pop":5.8}]},{"actorId":5293,"movies":[{"id":559,"title":"Spider-Man 3","poster":null,"pop":13.8},{"id":1951,"title":"Manderlay","poster":null,"pop":3.7}]},{"actorId":4785,"movies":[{"id":507086,"title":"Jurassic World Dominion","poster":null,"pop":14.9},{"id":351286,"title":"Jurassic World: Fallen Kingdom","poster":null,"pop":12.1}]},{"actorId":3894,"movies":[{"id":534,"title":"Terminator Salvation","poster":null,"pop":8.8}]},{"actorId":17052,"movies":[{"id":559,"title":"Spider-Man 3","poster":null,"pop":13.8}]},{"actorId":4654,"movies":[{"id":1951,"title":"Manderlay","poster":null,"pop":3.7}]},{"actorId":21029,"movies":[{"id":24021,"title":"The Twilight Saga: Eclipse","poster":null,"pop":9.4}]},{"actorId":45386,"movies":[{"id":8871,"title":"How the Grinch Stole Christmas","poster":null,"pop":30.8}]},{"actorId":37917,"movies":[{"id":24021,"title":"The Twilight Saga: Eclipse","poster":null,"pop":9.4}]},{"actorId":97446,"movies":[{"id":135397,"title":"Jurassic World","poster":null,"pop":15.1}]},{"actorId":84214,"movies":[{"id":24021,"title":"The Twilight Saga: Eclipse","poster":null,"pop":9.4}]},{"actorId":825,"movies":[{"id":334524,"title":"Gold","poster":null,"pop":5.8}]},{"actorId":11288,"movies":[{"id":24021,"title":"The Twilight Saga: Eclipse","poster":null,"pop":9.4}]},{"actorId":209513,"movies":[{"id":334524,"title":"Gold","poster":null,"pop":5.8}]},{"actorId":109438,"movies":[{"id":24021,"title":"The Twilight Saga: Eclipse","poster":null,"pop":9.4}]},{"actorId":4783,"movies":[{"id":507086,"title":"Jurassic World Dominion","poster":null,"pop":14.9}]},{"actorId":17419,"movies":[{"id":848538,"title":"Argylle","poster":null,"pop":5.9}]},{"actorId":8977,"movies":[{"id":334524,"title":"Gold","poster":null,"pop":5.8}]},{"actorId":21089,"movies":[{"id":334524,"title":"Gold","poster":null,"pop":5.8}]},{"actorId":4784,"movies":[{"id":507086,"title":"Jurassic World Dominion","poster":null,"pop":14.9}]},{"actorId":56857,"movies":[{"id":24021,"title":"The Twilight Saga: Eclipse","poster":null,"pop":9.4}]},{"actorId":55152,"movies":[{"id":507086,"title":"Jurassic World Dominion","poster":null,"pop":14.9}]},{"actorId":1091324,"movies":[{"id":848538,"title":"Argylle","poster":null,"pop":5.9}]},{"actorId":7132,"movies":[{"id":135397,"title":"Jurassic World","poster":null,"pop":15.1}]},{"actorId":4238,"movies":[{"id":534,"title":"Terminator Salvation","poster":null,"pop":8.8}]},{"actorId":73968,"movies":[{"id":848538,"title":"Argylle","poster":null,"pop":5.9}]},{"actorId":5606,"movies":[{"id":50014,"title":"The Help","poster":null,"pop":9.8}]},{"actorId":74541,"movies":[{"id":334524,"title":"Gold","poster":null,"pop":5.8}]},{"actorId":28640,"movies":[{"id":8871,"title":"How the Grinch Stole Christmas","poster":null,"pop":30.8}]},{"actorId":6916,"movies":[{"id":351286,"title":"Jurassic World: Fallen Kingdom","poster":null,"pop":12.1}]},{"actorId":6807,"movies":[{"id":848538,"title":"Argylle","poster":null,"pop":5.9}]},{"actorId":543505,"movies":[{"id":135397,"title":"Jurassic World","poster":null,"pop":15.1}]},{"actorId":65731,"movies":[{"id":534,"title":"Terminator Salvation","poster":null,"pop":8.8}]},{"actorId":1083177,"movies":[{"id":351286,"title":"Jurassic World: Fallen Kingdom","poster":null,"pop":12.1}]},{"actorId":41379,"movies":[{"id":1239193,"title":"Deep Cover","poster":null,"pop":6.8}]},{"actorId":2047,"movies":[{"id":1951,"title":"Manderlay","poster":null,"pop":3.7}]},{"actorId":2963838,"movies":[{"id":848538,"title":"Argylle","poster":null,"pop":5.9}]},{"actorId":206,"movies":[{"id":8871,"title":"How the Grinch Stole Christmas","poster":null,"pop":30.8}]},{"actorId":76543,"movies":[{"id":534,"title":"Terminator Salvation","poster":null,"pop":8.8}]},{"actorId":4812,"movies":[{"id":1951,"title":"Manderlay","poster":null,"pop":3.7}]},{"actorId":19159,"movies":[{"id":559,"title":"Spider-Man 3","poster":null,"pop":13.8}]},{"actorId":34502,"movies":[{"id":24021,"title":"The Twilight Saga: Eclipse","poster":null,"pop":9.4}]},{"actorId":20750,"movies":[{"id":135397,"title":"Jurassic World","poster":null,"pop":15.1}]},{"actorId":2838,"movies":[{"id":1951,"title":"Manderlay","poster":null,"pop":3.7}]},{"actorId":48,"movies":[{"id":1239193,"title":"Deep Cover","poster":null,"pop":6.8}]},{"actorId":121868,"movies":[{"id":24021,"title":"The Twilight Saga: Eclipse","poster":null,"pop":9.4}]},{"actorId":45827,"movies":[{"id":24021,"title":"The Twilight Saga: Eclipse","poster":null,"pop":9.4}]},{"actorId":53256,"movies":[{"id":534,"title":"Terminator Salvation","poster":null,"pop":8.8}]},{"actorId":13014,"movies":[{"id":351286,"title":"Jurassic World: Fallen Kingdom","poster":null,"pop":12.1}]},{"actorId":11357,"movies":[{"id":559,"title":"Spider-Man 3","poster":null,"pop":13.8}]},{"actorId":2219,"movies":[{"id":559,"title":"Spider-Man 3","poster":null,"pop":13.8}]},{"actorId":5657,"movies":[{"id":40807,"title":"50/50","poster":null,"pop":5.1}]},{"actorId":2453,"movies":[{"id":50014,"title":"The Help","poster":null,"pop":9.8}]},{"actorId":205,"movies":[{"id":559,"title":"Spider-Man 3","poster":null,"pop":13.8}]},{"actorId":168875,"movies":[{"id":135397,"title":"Jurassic World","poster":null,"pop":15.1}]},{"actorId":30697,"movies":[{"id":8871,"title":"How the Grinch Stole Christmas","poster":null,"pop":30.8}]},{"actorId":4492,"movies":[{"id":40807,"title":"50/50","poster":null,"pop":5.1}]},{"actorId":28847,"movies":[{"id":351286,"title":"Jurassic World: Fallen Kingdom","poster":null,"pop":12.1}]},{"actorId":1283,"movies":[{"id":534,"title":"Terminator Salvation","poster":null,"pop":8.8}]},{"actorId":19,"movies":[{"id":50014,"title":"The Help","poster":null,"pop":9.8}]},{"actorId":83002,"movies":[{"id":50014,"title":"The Help","poster":null,"pop":9.8}]},{"actorId":24045,"movies":[{"id":40807,"title":"50/50","poster":null,"pop":5.1}]},{"actorId":11086,"movies":[{"id":534,"title":"Terminator Salvation","poster":null,"pop":8.8}]},{"actorId":18999,"movies":[{"id":559,"title":"Spider-Man 3","poster":null,"pop":13.8}]},{"actorId":19492,"movies":[{"id":50014,"title":"The Help","poster":null,"pop":9.8}]},{"actorId":7624,"movies":[{"id":559,"title":"Spider-Man 3","poster":null,"pop":13.8}]},{"actorId":400,"movies":[{"id":351286,"title":"Jurassic World: Fallen Kingdom","poster":null,"pop":12.1}]},{"actorId":11769,"movies":[{"id":559,"title":"Spider-Man 3","poster":null,"pop":13.8}]},{"actorId":6944,"movies":[{"id":50014,"title":"The Help","poster":null,"pop":9.8}]},{"actorId":59252,"movies":[{"id":24021,"title":"The Twilight Saga: Eclipse","poster":null,"pop":9.4}]},{"actorId":114,"movies":[{"id":1239193,"title":"Deep Cover","poster":null,"pop":6.8}]},{"actorId":15854,"movies":[{"id":351286,"title":"Jurassic World: Fallen Kingdom","poster":null,"pop":12.1}]},{"actorId":6972,"movies":[{"id":1239193,"title":"Deep Cover","poster":null,"pop":6.8}]},{"actorId":9281,"movies":[{"id":559,"title":"Spider-Man 3","poster":null,"pop":13.8}]},{"actorId":14887,"movies":[{"id":1239193,"title":"Deep Cover","poster":null,"pop":6.8}]},{"actorId":11870,"movies":[{"id":8871,"title":"How the Grinch Stole Christmas","poster":null,"pop":30.8}]},{"actorId":501,"movies":[{"id":24021,"title":"The Twilight Saga: Eclipse","poster":null,"pop":9.4}]},{"actorId":59206,"movies":[{"id":559,"title":"Spider-Man 3","poster":null,"pop":13.8}]},{"actorId":10297,"movies":[{"id":334524,"title":"Gold","poster":null,"pop":5.8}]},{"actorId":58549,"movies":[{"id":8871,"title":"How the Grinch Stole Christmas","poster":null,"pop":30.8}]},{"actorId":19274,"movies":[{"id":40807,"title":"50/50","poster":null,"pop":5.1}]},{"actorId":54693,"movies":[{"id":50014,"title":"The Help","poster":null,"pop":9.8}]},{"actorId":52885,"movies":[{"id":50014,"title":"The Help","poster":null,"pop":9.8}]},{"actorId":2231,"movies":[{"id":848538,"title":"Argylle","poster":null,"pop":5.9}]},{"actorId":5049,"movies":[{"id":1951,"title":"Manderlay","poster":null,"pop":3.7}]},{"actorId":11514,"movies":[{"id":848538,"title":"Argylle","poster":null,"pop":5.9}]},{"actorId":4175,"movies":[{"id":8871,"title":"How the Grinch Stole Christmas","poster":null,"pop":30.8}]},{"actorId":15661,"movies":[{"id":8871,"title":"How the Grinch Stole Christmas","poster":null,"pop":30.8}]},{"actorId":22250,"movies":[{"id":8871,"title":"How the Grinch Stole Christmas","poster":null,"pop":30.8}]},{"actorId":1295,"movies":[{"id":8871,"title":"How the Grinch Stole Christmas","poster":null,"pop":30.8}]},{"actorId":17181,"movies":[{"id":135397,"title":"Jurassic World","poster":null,"pop":15.1}]},{"actorId":17051,"movies":[{"id":559,"title":"Spider-Man 3","poster":null,"pop":13.8}]},{"actorId":19152,"movies":[{"id":559,"title":"Spider-Man 3","poster":null,"pop":13.8}]},{"actorId":5502,"movies":[{"id":559,"title":"Spider-Man 3","poster":null,"pop":13.8}]},{"actorId":2368,"movies":[{"id":559,"title":"Spider-Man 3","poster":null,"pop":13.8}]},{"actorId":20580,"movies":[{"id":559,"title":"Spider-Man 3","poster":null,"pop":13.8}]},{"actorId":53755,"movies":[{"id":24021,"title":"The Twilight Saga: Eclipse","poster":null,"pop":9.4}]},{"actorId":84215,"movies":[{"id":24021,"title":"The Twilight Saga: Eclipse","poster":null,"pop":9.4}]},{"actorId":84225,"movies":[{"id":24021,"title":"The Twilight Saga: Eclipse","poster":null,"pop":9.4}]},{"actorId":56446,"movies":[{"id":848538,"title":"Argylle","poster":null,"pop":5.9}]},{"actorId":20766,"movies":[{"id":848538,"title":"Argylle","poster":null,"pop":5.9}]},{"actorId":1381548,"movies":[{"id":848538,"title":"Argylle","poster":null,"pop":5.9}]},{"actorId":41436,"movies":[{"id":40807,"title":"50/50","poster":null,"pop":5.1}]},{"actorId":20286,"movies":[{"id":334524,"title":"Gold","poster":null,"pop":5.8}]},{"actorId":121718,"movies":[{"id":334524,"title":"Gold","poster":null,"pop":5.8}]},{"actorId":6752,"movies":[{"id":1951,"title":"Manderlay","poster":null,"pop":3.7}]},{"actorId":1646,"movies":[{"id":1951,"title":"Manderlay","poster":null,"pop":3.7}]}]}